<?xml version="1.0" encoding="UTF-8"?>
<npc_walker xmlns:xsi="http://www.w3.org/2001/XMLSchema-instance" xmlns:xsd="http://www.w3.org/2001/XMLSchema">
    <walker_template route_id="iddreadgion_02_path_39" pool="1">
	    <routestep step="1" x="491.72314" y="835.7460" z="416.3750"/>
		<routestep step="2" x="483.95926" y="836.16187" z="416.37442"/>
		<routestep step="3" x="472.91193" y="834.24023" z="416.3752"/>
		<routestep step="4" x="466.22574" y="827.8280" z="416.4650"/>
		<routestep step="5" x="467.77182" y="824.68823" z="416.63818"/>
		<routestep step="6" x="474.24466" y="829.73474" z="416.62027"/>
		<routestep step="7" x="484.00656" y="831.96405" z="416.63516"/>
		<routestep step="8" x="495.12466" y="829.81647" z="416.633"/>
		<routestep step="9" x="505.14377" y="824.3093" z="416.6355"/>
		<routestep step="10" x="507.38675" y="826.71686" z="416.3754"/>
		<routestep step="11" x="498.13702" y="833.3858" z="416.37527"/>
		<routestep step="12" x="493.56647" y="834.94794" z="416.3752"/>
    </walker_template>
    <walker_template route_id="path_iddreadgion_02_drakanas_55_ae_1_1" pool="1">
	    <routestep step="1" x="433.6000" y="496.8700" z="393.43066"/>
		<routestep step="2" x="428.20908" y="503.68735" z="392.94437"/>
		<routestep step="3" x="421.6524" y="509.74023" z="392.70834"/>
		<routestep step="4" x="411.51407" y="511.43948" z="393.50027"/>
		<routestep step="5" x="411.49838" y="510.99878" z="393.54263"/>
		<routestep step="6" x="421.32114" y="509.30692" z="392.70834"/>
		<routestep step="7" x="427.7839" y="503.40726" z="392.8639"/>
		<routestep step="8" x="433.4914" y="496.17984" z="393.3934"/>
    </walker_template>
    <walker_template route_id="path_iddreadgion_02_drakanas_55_ae_2_1" pool="1">
	    <routestep step="1" x="533.4212" y="495.1569" z="393.50827"/>
		<routestep step="2" x="541.46967" y="501.90805" z="393.49445"/>
		<routestep step="3" x="547.01953" y="505.98422" z="392.70834"/>
		<routestep step="4" x="558.1415" y="511.44763" z="393.56076"/>
		<routestep step="5" x="558.1258" y="511.0069" z="393.60565"/>
		<routestep step="6" x="547.4251" y="505.6076" z="392.7083"/>
		<routestep step="7" x="542.15027" y="501.68466" z="393.4175"/>
		<routestep step="8" x="533.31256" y="494.46674" z="393.49466"/>
    </walker_template>
    <walker_template route_id="path_iddreadgion_02_drakanasnoble_55_ae_1_1" pool="1">
	    <routestep step="1" x="472.6182" y="851.2217" z="417.11108"/>
		<routestep step="2" x="462.97177" y="857.87024" z="414.69873"/>
		<routestep step="3" x="457.0532" y="866.88947" z="410.60422"/>
		<routestep step="4" x="454.73416" y="877.9368" z="407.5176"/>
		<routestep step="5" x="456.5803" y="891.24493" z="405.3160"/>
		<routestep step="6" x="457.40067" y="891.42523" z="405.29947"/>
		<routestep step="7" x="455.27823" y="878.0253" z="407.49353"/>
		<routestep step="8" x="457.6839" y="866.3514" z="410.83374"/>
		<routestep step="9" x="463.25964" y="857.5274" z="414.8623"/>
		<routestep step="10" x="472.50958" y="850.5315" z="417.06097"/>
    </walker_template>
    <walker_template route_id="path_iddreadgion_02_drakanasnoble_55_ae_2_1" pool="1">
	    <routestep step="1" x="495.75598" y="850.8360" z="417.07437"/>
		<routestep step="2" x="503.4502" y="855.14453" z="416.3969"/>
		<routestep step="3" x="510.79456" y="861.3620" z="412.5919"/>
		<routestep step="4" x="514.75635" y="873.1510" z="408.81766"/>
		<routestep step="5" x="514.15875" y="887.11127" z="405.25897"/>
		<routestep step="6" x="514.9792" y="887.29156" z="405.26352"/>
		<routestep step="7" x="515.3004" y="873.2395" z="408.77332"/>
		<routestep step="8" x="511.42526" y="860.8239" z="412.67093"/>
		<routestep step="9" x="503.73807" y="854.8017" z="416.3639"/>
		<routestep step="10" x="495.64737" y="850.1458" z="417.02335"/>
    </walker_template>
    <walker_template route_id="path_iddreadgion_02_drakanaswait_55_ae_1" pool="1">
	    <routestep step="1" x="479.3800" y="494.0300" z="396.99127"/>
		<routestep step="2" x="482.03482" y="488.77563" z="396.85638"/>
		<routestep step="3" x="488.20023" y="488.88162" z="396.8673"/>
		<routestep step="4" x="491.88184" y="492.82895" z="396.88678"/>
		<routestep step="5" x="491.88815" y="498.11218" z="396.89893"/>
		<routestep step="6" x="488.16235" y="502.77463" z="396.83807"/>
		<routestep step="7" x="482.1435" y="502.88806" z="396.82898"/>
		<routestep step="8" x="479.37726" y="498.57214" z="396.94693"/>
		<routestep step="9" x="479.2714" y="493.33984" z="396.96814"/>
    </walker_template>
    <walker_template route_id="path_iddreadgion_02_drakanclhigh_55_ae_1_1" pool="1">
	    <routestep step="1" x="490.40372" y="304.08676" z="403.31293"/>
		<routestep step="2" x="485.31482" y="302.8269" z="403.34183"/>
		<routestep step="3" x="478.04398" y="304.90704" z="403.37332"/>
		<routestep step="4" x="472.92932" y="311.19714" z="403.42978"/>
		<routestep step="5" x="473.87576" y="320.9199" z="403.09518"/>
		<routestep step="6" x="480.06207" y="325.72202" z="403.23093"/>
		<routestep step="7" x="485.7797" y="326.21344" z="403.36386"/>
		<routestep step="8" x="496.00006" y="322.65326" z="402.88074"/>
		<routestep step="9" x="498.21793" y="311.91324" z="403.01453"/>
		<routestep step="10" x="492.13425" y="304.76523" z="403.36996"/>
    </walker_template>
    <walker_template route_id="path_iddreadgion_02_drakanclhigh_55_ae_4_1" pool="1">
	    <routestep step="1" x="395.31006" y="715.1077" z="401.95728"/>
		<routestep step="2" x="391.94193" y="716.3879" z="402.07083"/>
		<routestep step="3" x="388.56998" y="715.02795" z="402.07037"/>
		<routestep step="4" x="386.8962" y="711.82294" z="401.8863"/>
		<routestep step="5" x="387.82727" y="707.79675" z="401.7724"/>
		<routestep step="6" x="392.1431" y="705.42303" z="401.7698"/>
		<routestep step="7" x="396.15787" y="707.17065" z="401.86166"/>
		<routestep step="8" x="397.45706" y="711.2340" z="401.8857"/>
		<routestep step="9" x="395.1866" y="715.4863" z="402.07672"/>
    </walker_template>
    <walker_template route_id="path_iddreadgion_02_drakanclhigh_55_ae_5_1" pool="1">
	    <routestep step="1" x="581.2154" y="715.60675" z="402.14737"/>
		<routestep step="2" x="577.8473" y="716.8869" z="402.30444"/>
		<routestep step="3" x="574.47534" y="715.5270" z="402.3170"/>
		<routestep step="4" x="572.8016" y="712.32196" z="402.03152"/>
		<routestep step="5" x="573.7326" y="708.2958" z="401.7698"/>
		<routestep step="6" x="578.04846" y="705.92206" z="401.7698"/>
		<routestep step="7" x="582.06323" y="707.6697" z="401.7698"/>
		<routestep step="8" x="583.3624" y="711.73303" z="401.90842"/>
		<routestep step="9" x="581.0919" y="715.98535" z="402.29926"/>
    </walker_template>
    <walker_template route_id="path_iddreadgion_02_drakanclhigh_55_ae_6_1" pool="1">
	    <routestep step="1" x="496.5100" y="598.11316" z="390.65936"/>
		<routestep step="2" x="490.82376" y="605.14496" z="390.9229"/>
		<routestep step="3" x="481.34515" y="606.2240" z="390.93195"/>
		<routestep step="4" x="470.88785" y="603.40985" z="390.39767"/>
		<routestep step="5" x="471.25638" y="602.8884" z="390.39767"/>
		<routestep step="6" x="481.39215" y="605.68054" z="390.9358"/>
		<routestep step="7" x="490.74197" y="604.6503" z="390.9244"/>
		<routestep step="8" x="496.4014" y="597.4230" z="390.78983"/>
    </walker_template>
    <walker_template route_id="path_iddreadgion_02_drakanfi_55_ae_2_1" pool="1">
	    <routestep step="1" x="426.10446" y="477.94247" z="393.28854"/>
		<routestep step="2" x="427.01868" y="484.7598" z="393.1686"/>
		<routestep step="3" x="427.0226" y="491.5430" z="393.1953"/>
		<routestep step="4" x="419.80515" y="491.86356" z="393.45325"/>
		<routestep step="5" x="418.07642" y="483.05243" z="393.15823"/>
		<routestep step="6" x="425.99585" y="477.25232" z="393.27505"/>
    </walker_template>
    <walker_template route_id="path_iddreadgion_02_drakanfi_55_ae_4_1" pool="1">
	    <routestep step="1" x="543.7737" y="481.3166" z="393.2115"/>
		<routestep step="2" x="550.90985" y="472.91006" z="393.27106"/>
		<routestep step="3" x="556.2776" y="474.72488" z="392.85107"/>
		<routestep step="4" x="553.7572" y="485.17664" z="393.35416"/>
		<routestep step="5" x="545.3452" y="489.67047" z="393.21295"/>
		<routestep step="6" x="543.66504" y="480.62643" z="393.23727"/>
    </walker_template>
    <walker_template route_id="path_iddreadgion_02_drakanmahigh_55_ae_2_1" pool="1">
	    <routestep step="1" x="369.35208" y="421.4293" z="411.08752"/>
		<routestep step="2" x="360.53406" y="425.60574" z="410.67902"/>
		<routestep step="3" x="352.00928" y="432.0647" z="410.50504"/>
		<routestep step="4" x="341.26596" y="427.7901" z="409.9537"/>
		<routestep step="5" x="335.27924" y="416.2509" z="411.06616"/>
		<routestep step="6" x="340.54523" y="404.2514" z="410.6603"/>
		<routestep step="7" x="353.31824" y="402.5001" z="411.41086"/>
		<routestep step="8" x="367.0832" y="411.54587" z="410.57742"/>
		<routestep step="9" x="369.83112" y="419.63544" z="411.03302"/>
    </walker_template>
    <walker_template route_id="path_iddreadgion_02_drakanmahigh_55_ae_3_1" pool="1">
	    <routestep step="1" x="600.7570" y="423.48904" z="411.6610"/>
		<routestep step="2" x="616.3301" y="432.6440" z="411.24295"/>
		<routestep step="3" x="632.6915" y="427.6664" z="410.3111"/>
		<routestep step="4" x="638.20514" y="415.268" z="410.76617"/>
		<routestep step="5" x="634.79376" y="397.25067" z="411.33258"/>
		<routestep step="6" x="620.7706" y="396.61856" z="412.18924"/>
		<routestep step="7" x="609.2051" y="407.0568" z="410.4225"/>
		<routestep step="8" x="602.0942" y="414.94934" z="410.50836"/>
		<routestep step="9" x="599.0343" y="422.29895" z="411.5912"/>
    </walker_template>
    <walker_template route_id="path_iddreadgion_02_drakanmahigh_55_ae_4_1" pool="1">
	    <routestep step="1" x="384.5325" y="546.33093" z="409.96188"/>
		<routestep step="2" x="378.20142" y="546.07007" z="409.85864"/>
		<routestep step="3" x="372.8087" y="550.83856" z="408.77185"/>
		<routestep step="4" x="373.14542" y="551.13293" z="408.79132"/>
		<routestep step="5" x="378.44827" y="546.38556" z="409.8743"/>
		<routestep step="6" x="385.1342" y="546.5767" z="409.97266"/>
		<routestep step="7" x="389.76486" y="548.1400" z="409.99826"/>
		<routestep step="8" x="396.07434" y="552.97064" z="409.68265"/>
		<routestep step="9" x="396.34616" y="552.7427" z="409.69354"/>
		<routestep step="10" x="390.1384" y="547.99615" z="409.99518"/>
		<routestep step="11" x="385.28464" y="546.23096" z="409.98453"/>
    </walker_template>
    <walker_template route_id="path_iddreadgion_02_drakanmahigh_55_ae_5_1" pool="1">
	    <routestep step="1" x="584.70703" y="549.8315" z="410.33453"/>
		<routestep step="2" x="590.8564" y="551.03955" z="409.73505"/>
		<routestep step="3" x="598.87897" y="553.2890" z="408.46445"/>
		<routestep step="4" x="598.51746" y="553.7351" z="408.49393"/>
		<routestep step="5" x="590.64154" y="551.5995" z="409.73267"/>
		<routestep step="6" x="583.8169" y="550.3476" z="410.37598"/>
		<routestep step="7" x="577.7127" y="551.5689" z="410.2330"/>
		<routestep step="8" x="572.3358" y="556.5420" z="409.46594"/>
		<routestep step="9" x="572.1520" y="556.1015" z="409.5080"/>
		<routestep step="10" x="577.6551" y="551.15485" z="410.25317"/>
		<routestep step="11" x="583.5068" y="549.8165" z="410.4327"/>
    </walker_template>
    <walker_template route_id="path_iddreadgion_02_drakanrainspector_55_ah_1" pool="1">
	    <routestep step="1" x="484.5442" y="909.91736" z="405.25128"/>
		<routestep step="2" x="475.44522" y="908.2477" z="405.11884"/>
		<routestep step="3" x="468.27457" y="905.0462" z="405.30344"/>
		<routestep step="4" x="459.28583" y="897.5531" z="405.29794"/>
		<routestep step="5" x="459.8125" y="896.9260" z="405.28638"/>
		<routestep step="6" x="468.6336" y="904.2741" z="405.27957"/>
		<routestep step="7" x="475.37372" y="907.5638" z="405.12933"/>
		<routestep step="8" x="484.2268" y="909.0073" z="405.2370"/>
		<routestep step="9" x="492.05807" y="908.1882" z="405.20255"/>
		<routestep step="10" x="502.68546" y="903.97125" z="405.24384"/>
		<routestep step="11" x="509.14792" y="898.23914" z="405.19177"/>
		<routestep step="12" x="509.6820" y="898.6874" z="405.19052"/>
		<routestep step="13" x="503.18893" y="904.60284" z="405.25726"/>
		<routestep step="14" x="492.02444" y="908.73285" z="405.20496"/>
		<routestep step="15" x="485.6513" y="909.4041" z="405.24203"/>
    </walker_template>
    <walker_template route_id="path_iddreadgion_02_drakanschigh_55_ae_10_1" pool="1">
	    <routestep step="1" x="474.33017" y="590.37506" z="390.48114"/>
		<routestep step="2" x="479.45428" y="584.33075" z="390.43643"/>
		<routestep step="3" x="488.81454" y="583.7170" z="390.91974"/>
		<routestep step="4" x="498.1482" y="587.45667" z="391.12823"/>
		<routestep step="5" x="498.2238" y="586.86206" z="391.19052"/>
		<routestep step="6" x="488.86154" y="583.1735" z="390.9128"/>
		<routestep step="7" x="479.23416" y="584.0728" z="390.4666"/>
		<routestep step="8" x="474.22156" y="589.6849" z="390.46783"/>
    </walker_template>
    <walker_template route_id="path_iddreadgion_02_drakanschigh_55_ae_4_1" pool="1">
	    <routestep step="1" x="410.5970" y="572.9854" z="410.62518"/>
		<routestep step="2" x="408.5435" y="577.7706" z="410.42307"/>
		<routestep step="3" x="404.51224" y="581.6822" z="409.83127"/>
		<routestep step="4" x="404.80148" y="582.3406" z="409.79163"/>
		<routestep step="5" x="409.10767" y="578.0871" z="410.3798"/>
		<routestep step="6" x="411.6159" y="571.7433" z="410.55444"/>
		<routestep step="7" x="409.25464" y="560.50006" z="410.19977"/>
		<routestep step="8" x="403.32886" y="554.9495" z="409.69904"/>
		<routestep step="9" x="403.1499" y="555.13104" z="409.7133"/>
		<routestep step="10" x="408.8892" y="560.5233" z="410.23297"/>
		<routestep step="11" x="411.38797" y="571.7068" z="410.57755"/>
    </walker_template>
    <walker_template route_id="path_iddreadgion_02_drakanschigh_55_ae_5_1" pool="1">
	    <routestep step="1" x="559.2096" y="567.4457" z="410.31625"/>
		<routestep step="2" x="557.0429" y="574.9972" z="410.30215"/>
		<routestep step="3" x="558.64734" y="583.82654" z="409.25592"/>
		<routestep step="4" x="559.27435" y="583.5567" z="409.20496"/>
		<routestep step="5" x="557.64453" y="575.09534" z="410.3014"/>
		<routestep step="6" x="559.90314" y="567.83594" z="410.29373"/>
		<routestep step="7" x="563.2429" y="564.0189" z="410.16348"/>
		<routestep step="8" x="568.6605" y="559.3774" z="409.60968"/>
		<routestep step="9" x="568.4767" y="558.9369" z="409.57977"/>
		<routestep step="10" x="563.1853" y="563.60486" z="410.1533"/>
		<routestep step="11" x="559.68256" y="566.83325" z="410.3153"/>
    </walker_template>
    <walker_template route_id="path_iddreadgion_02_drakanschigh_55_ae_7_1" pool="1">
	    <routestep step="1" x="381.67926" y="721.1001" z="402.23694"/>
		<routestep step="2" x="380.0832" y="727.21704" z="403.1211"/>
		<routestep step="3" x="375.85876" y="735.72705" z="405.17087"/>
		<routestep step="4" x="373.82272" y="750.50745" z="407.86453"/>
		<routestep step="5" x="380.75375" y="767.6460" z="410.61926"/>
		<routestep step="6" x="400.16782" y="779.11597" z="412.5804"/>
		<routestep step="7" x="416.96826" y="785.96954" z="413.4282"/>
		<routestep step="8" x="427.60574" y="791.95416" z="413.45618"/>
		<routestep step="9" x="427.0313" y="793.6255" z="413.4452"/>
		<routestep step="10" x="416.10358" y="788.1350" z="413.42953"/>
		<routestep step="11" x="399.1117" y="780.5623" z="412.57913"/>
		<routestep step="12" x="379.84668" y="768.7248" z="410.68988"/>
		<routestep step="13" x="372.87958" y="750.54834" z="407.86905"/>
		<routestep step="14" x="375.27005" y="735.5608" z="405.2010"/>
		<routestep step="15" x="379.6420" y="726.7281" z="403.11002"/>
		<routestep step="16" x="381.55582" y="721.4787" z="402.23737"/>
    </walker_template>
    <walker_template route_id="path_iddreadgion_02_drakanschigh_55_ae_8_1" pool="1">
	    <routestep step="1" x="587.67975" y="719.1108" z="402.23398"/>
		<routestep step="2" x="593.72363" y="727.6509" z="403.79877"/>
		<routestep step="3" x="597.3364" y="739.2194" z="406.2957"/>
		<routestep step="4" x="596.42883" y="754.7852" z="408.53946"/>
		<routestep step="5" x="587.25085" y="767.22894" z="410.72607"/>
		<routestep step="6" x="575.99133" y="776.7681" z="412.19998"/>
		<routestep step="7" x="560.1301" y="782.74335" z="413.12527"/>
		<routestep step="8" x="543.4531" y="791.80054" z="413.45508"/>
		<routestep step="9" x="543.3814" y="790.5324" z="413.4690"/>
		<routestep step="10" x="559.84625" y="781.5781" z="413.11584"/>
		<routestep step="11" x="575.324" y="775.80414" z="412.19528"/>
		<routestep step="12" x="586.13684" y="767.02515" z="410.81085"/>
		<routestep step="13" x="595.52856" y="754.0084" z="408.4293"/>
		<routestep step="14" x="596.7477" y="739.05316" z="406.19388"/>
		<routestep step="15" x="593.2276" y="727.9419" z="403.7715"/>
		<routestep step="16" x="587.5563" y="719.4894" z="402.2337"/>
    </walker_template>
    <walker_template route_id="path_iddreadgion_02_lizardas_55_ae_6_1" pool="1">
	    <routestep step="1" x="480.26135" y="473.98413" z="398.03217"/>
		<routestep step="2" x="482.23465" y="467.5331" z="398.22388"/>
		<routestep step="3" x="490.37744" y="468.85898" z="398.2069"/>
		<routestep step="4" x="491.7813" y="478.15076" z="397.90857"/>
		<routestep step="5" x="484.7986" y="482.5955" z="397.59494"/>
		<routestep step="6" x="480.2586" y="478.52628" z="397.87363"/>
		<routestep step="7" x="480.15274" y="473.29398" z="398.06107"/>
    </walker_template>
    <walker_template route_id="path_iddreadgion_02_lizardas_55_ae_7_1" pool="1">
	    <routestep step="1" x="492.07895" y="514.0005" z="397.93872"/>
		<routestep step="2" x="485.01688" y="509.63818" z="397.7442"/>
		<routestep step="3" x="478.9654" y="512.4509" z="397.8754"/>
		<routestep step="4" x="479.75623" y="519.753" z="398.12027"/>
		<routestep step="5" x="484.13284" y="524.9451" z="397.9111"/>
		<routestep step="6" x="487.7618" y="519.8471" z="398.1115"/>
		<routestep step="7" x="491.97034" y="513.3103" z="397.91324"/>
    </walker_template>
    <walker_template route_id="path_iddreadgion_02_lizardbroada_55_a_1" pool="1">
	    <routestep step="1" x="425.8300" y="261.0700" z="409.99112"/>
		<routestep step="2" x="426.37814" y="256.60962" z="410.81717"/>
		<routestep step="3" x="427.1761" y="246.27383" z="413.54214"/>
		<routestep step="4" x="424.6473" y="217.40138" z="422.98053"/>
		<routestep step="5" x="423.96484" y="217.40619" z="423.00458"/>
		<routestep step="6" x="426.0579" y="248.50586" z="412.79645"/>
		<routestep step="7" x="425.70407" y="256.5115" z="410.63043"/>
		<routestep step="8" x="425.39032" y="261.15698" z="410.03693"/>
    </walker_template>
    <walker_template route_id="path_iddreadgion_02_lizardbroadb_55_ae_1" pool="1">
	    <routestep step="1" x="547.48987" y="264.96066" z="409.73868"/>
		<routestep step="2" x="545.85834" y="261.9760" z="409.82034"/>
		<routestep step="3" x="543.78687" y="250.5197" z="412.22208"/>
		<routestep step="4" x="545.9933" y="220.1248" z="422.2858"/>
		<routestep step="5" x="545.31085" y="220.06737" z="422.26578"/>
		<routestep step="6" x="543.0354" y="250.81552" z="412.40344"/>
		<routestep step="7" x="545.18427" y="261.8779" z="409.81747"/>
		<routestep step="8" x="547.05023" y="265.04764" z="409.73874"/>
    </walker_template>
    <walker_template route_id="path_iddreadgion_02_lizardfi_55_ae_6_1" pool="1">
	    <routestep step="1" x="346.76965" y="392.53503" z="412.13235"/>
		<routestep step="2" x="335.0992" y="399.84344" z="411.47525"/>
		<routestep step="3" x="327.8872" y="413.48755" z="411.91507"/>
		<routestep step="4" x="328.17328" y="429.4331" z="410.8640"/>
		<routestep step="5" x="329.1474" y="429.42398" z="410.6992"/>
		<routestep step="6" x="328.58588" y="413.56583" z="411.87103"/>
		<routestep step="7" x="335.71594" y="400.12146" z="411.4229"/>
		<routestep step="8" x="347.09573" y="394.4440" z="412.0301"/>
		<routestep step="9" x="357.1572" y="391.85547" z="412.67322"/>
		<routestep step="10" x="367.89572" y="398.64664" z="411.70813"/>
		<routestep step="11" x="368.44254" y="398.13297" z="411.7282"/>
		<routestep step="12" x="357.2478" y="391.3037" z="412.71243"/>
		<routestep step="13" x="348.0168" y="393.4956" z="412.16327"/>
    </walker_template>
    <walker_template route_id="path_iddreadgion_02_lizardfi_55_ae_9_1" pool="1">
	    <routestep step="1" x="628.7806" y="386.38574" z="412.91882"/>
		<routestep step="2" x="642.5454" y="394.79156" z="410.8733"/>
		<routestep step="3" x="646.9767" y="409.40833" z="412.10425"/>
		<routestep step="4" x="644.06384" y="425.4530" z="411.46255"/>
		<routestep step="5" x="643.1119" y="425.0795" z="411.35748"/>
		<routestep step="6" x="646.0111" y="409.22653" z="412.0692"/>
		<routestep step="7" x="641.8978" y="395.62286" z="410.91537"/>
		<routestep step="8" x="629.1067" y="388.2947" z="412.82123"/>
		<routestep step="9" x="615.7150" y="392.22107" z="412.79858"/>
		<routestep step="10" x="606.7673" y="399.44833" z="411.52185"/>
		<routestep step="11" x="606.46515" y="398.8961" z="411.5717"/>
		<routestep step="12" x="615.8056" y="391.6693" z="412.8545"/>
		<routestep step="13" x="630.0277" y="387.3463" z="412.8060"/>
    </walker_template>
    <walker_template route_id="path_iddreadgion_02_lizardpr_55_ae_1_1" pool="1">
	    <routestep step="1" x="420.8330" y="273.0195" z="409.7311"/>
		<routestep step="2" x="415.9331" y="271.83414" z="409.7311"/>
		<routestep step="3" x="410.44534" y="272.95285" z="409.7311"/>
		<routestep step="4" x="405.70056" y="274.10745" z="409.74985"/>
		<routestep step="5" x="405.81543" y="274.5352" z="409.736"/>
		<routestep step="6" x="410.50974" y="273.37582" z="409.7311"/>
		<routestep step="7" x="415.9524" y="272.30966" z="409.7311"/>
		<routestep step="8" x="420.2409" y="273.39478" z="409.7311"/>
		<routestep step="9" x="425.82895" y="278.61572" z="409.7311"/>
		<routestep step="10" x="429.28842" y="283.3489" z="409.7311"/>
		<routestep step="11" x="429.58047" y="283.1692" z="409.7317"/>
		<routestep step="12" x="426.1106" y="278.43445" z="409.7311"/>
		<routestep step="13" x="421.5202" y="273.7283" z="409.7311"/>
    </walker_template>
    <walker_template route_id="path_iddreadgion_02_lizardpr_55_ae_2_1" pool="1">
	    <routestep step="1" x="552.8298" y="272.0853" z="409.7311"/>
		<routestep step="2" x="546.9364" y="276.4878" z="409.7311"/>
		<routestep step="3" x="543.0559" y="279.44617" z="409.7311"/>
		<routestep step="4" x="539.7677" y="284.08148" z="409.7311"/>
		<routestep step="5" x="539.88257" y="284.50922" z="409.73367"/>
		<routestep step="6" x="543.12024" y="279.86914" z="409.7311"/>
		<routestep step="7" x="546.9557" y="276.96332" z="409.7311"/>
		<routestep step="8" x="552.2377" y="272.46057" z="409.7311"/>
		<routestep step="9" x="558.9996" y="272.56125" z="409.7311"/>
		<routestep step="10" x="565.5287" y="275.14587" z="409.9257"/>
		<routestep step="11" x="565.8208" y="274.96616" z="409.96774"/>
		<routestep step="12" x="559.28125" y="272.37997" z="409.7311"/>
		<routestep step="13" x="553.27686" y="272.7806" z="409.7311"/>
    </walker_template>
    <walker_template route_id="path_iddreadgion_02_lizardra_55_ae_1_1" pool="1">
	    <routestep step="1" x="408.22354" y="297.0464" z="409.9302"/>
		<routestep step="2" x="415.70438" y="287.91183" z="409.7311"/>
		<routestep step="3" x="423.64114" y="298.70795" z="409.53925"/>
		<routestep step="4" x="441.20425" y="322.77155" z="403.40543"/>
		<routestep step="5" x="434.9303" y="326.5446" z="403.37402"/>
		<routestep step="6" x="417.28345" y="324.54544" z="402.67148"/>
		<routestep step="7" x="405.78714" y="323.23337" z="402.6441"/>
		<routestep step="8" x="404.6281" y="310.4422" z="407.22507"/>
		<routestep step="9" x="404.6580" y="305.3836" z="409.4079"/>
		<routestep step="10" x="407.9650" y="297.64096" z="409.918"/>
    </walker_template>
    <walker_template route_id="path_iddreadgion_02_lizardra_55_ae_2_1" pool="1">
	    <routestep step="1" x="562.6236" y="321.4818" z="402.94922"/>
		<routestep step="2" x="565.7551" y="312.7572" z="406.11832"/>
		<routestep step="3" x="563.33765" y="300.05338" z="410.08002"/>
		<routestep step="4" x="553.02686" y="296.80765" z="409.79562"/>
		<routestep step="5" x="543.7352" y="303.87585" z="408.13004"/>
		<routestep step="6" x="538.3717" y="310.17175" z="405.60495"/>
		<routestep step="7" x="533.25714" y="320.0225" z="404.45096"/>
		<routestep step="8" x="537.03735" y="325.83813" z="403.39984"/>
		<routestep step="9" x="547.84454" y="324.1487" z="403.0267"/>
		<routestep step="10" x="555.00073" y="324.78635" z="402.50955"/>
		<routestep step="11" x="561.2102" y="323.51755" z="402.5531"/>
    </walker_template>
    <walker_template route_id="path_iddreadgion_02_party1_1" pool="1">
	    <routestep step="1" x="402.64838" y="337.12213" z="402.37863"/>
		<routestep step="2" x="401.03177" y="340.4692" z="402.85532"/>
		<routestep step="3" x="400.4465" y="351.06824" z="402.7963"/>
		<routestep step="4" x="402.3142" y="362.80167" z="403.29242"/>
		<routestep step="5" x="406.6542" y="375.54974" z="407.26028"/>
		<routestep step="6" x="404.20282" y="383.0599" z="408.46674"/>
		<routestep step="7" x="399.66785" y="388.96286" z="409.8827"/>
		<routestep step="8" x="400.6992" y="389.50336" z="409.80203"/>
		<routestep step="9" x="405.1569" y="383.9501" z="408.4314"/>
		<routestep step="10" x="407.9567" y="375.6523" z="407.0710"/>
		<routestep step="11" x="403.25485" y="362.4986" z="403.06546"/>
		<routestep step="12" x="401.359" y="350.61383" z="402.9308"/>
		<routestep step="13" x="402.1607" y="340.72968" z="402.81345"/>
		<routestep step="14" x="403.44818" y="337.49237" z="402.40802"/>
    </walker_template>
    <walker_template route_id="path_iddreadgion_02_party2_1" pool="1">
	    <routestep step="1" x="569.3058" y="344.20395" z="403.15823"/>
		<routestep step="2" x="568.64105" y="352.58267" z="402.60843"/>
		<routestep step="3" x="567.6033" y="362.65448" z="403.1256"/>
		<routestep step="4" x="563.40173" y="369.3796" z="405.22604"/>
		<routestep step="5" x="562.8865" y="374.02765" z="406.57248"/>
		<routestep step="6" x="563.8698" y="382.14893" z="408.13144"/>
		<routestep step="7" x="567.3125" y="387.88846" z="409.23282"/>
		<routestep step="8" x="571.08875" y="392.4143" z="410.1252"/>
		<routestep step="9" x="576.15796" y="397.74426" z="410.31186"/>
		<routestep step="10" x="576.9834" y="397.03662" z="410.41193"/>
		<routestep step="11" x="571.5212" y="391.7659" z="410.10953"/>
		<routestep step="12" x="567.79956" y="387.2980" z="409.1832"/>
		<routestep step="13" x="564.4941" y="382.0772" z="408.11166"/>
		<routestep step="14" x="563.47986" y="374.19324" z="406.76602"/>
		<routestep step="15" x="564.06445" y="369.54526" z="405.37546"/>
		<routestep step="16" x="568.2295" y="362.78162" z="403.2435"/>
		<routestep step="17" x="569.39667" y="352.73895" z="402.5001"/>
		<routestep step="18" x="570.2710" y="344.47498" z="403.3777"/>
    </walker_template>
    <walker_template route_id="path_iddreadgion_02_party3_1" pool="1">
	    <routestep step="1" x="337.45822" y="461.0925" z="408.09512"/>
		<routestep step="2" x="337.6551" y="476.75778" z="402.23236"/>
		<routestep step="3" x="341.4219" y="493.27972" z="397.7670"/>
		<routestep step="4" x="344.6412" y="506.7784" z="398.63443"/>
		<routestep step="5" x="350.7943" y="523.85864" z="402.0083"/>
		<routestep step="6" x="355.7008" y="538.72516" z="405.73383"/>
		<routestep step="7" x="362.1639" y="550.6037" z="407.8515"/>
		<routestep step="8" x="362.95724" y="550.35547" z="407.9178"/>
		<routestep step="9" x="356.73514" y="538.2173" z="405.77835"/>
		<routestep step="10" x="351.71786" y="523.4776" z="402.13138"/>
		<routestep step="11" x="345.5537" y="506.7465" z="398.99918"/>
		<routestep step="12" x="342.37015" y="493.16943" z="397.57755"/>
		<routestep step="13" x="338.6758" y="476.8714" z="402.3007"/>
		<routestep step="14" x="338.25995" y="460.99045" z="408.10687"/>
    </walker_template>
    <walker_template route_id="path_iddreadgion_02_party4_1" pool="1">
	    <routestep step="1" x="630.28656" y="457.63837" z="408.53506"/>
		<routestep step="2" x="629.70557" y="467.15097" z="406.29956"/>
		<routestep step="3" x="630.1935" y="487.25995" z="399.05048"/>
		<routestep step="4" x="628.5813" y="501.7392" z="397.78162"/>
		<routestep step="5" x="622.8109" y="517.11884" z="400.46008"/>
		<routestep step="6" x="616.90326" y="530.5308" z="403.20816"/>
		<routestep step="7" x="609.8307" y="545.5131" z="407.6813"/>
		<routestep step="8" x="610.40314" y="545.7316" z="407.65753"/>
		<routestep step="9" x="617.65894" y="530.76495" z="403.09772"/>
		<routestep step="10" x="623.7345" y="516.73785" z="400.25552"/>
		<routestep step="11" x="629.4938" y="501.70728" z="397.8243"/>
		<routestep step="12" x="631.1417" y="487.14966" z="399.17566"/>
		<routestep step="13" x="630.7263" y="467.2646" z="406.16644"/>
		<routestep step="14" x="631.0883" y="457.53632" z="408.53806"/>
    </walker_template>
    <walker_template route_id="path_iddreadgion_02_party5_1" pool="1">
	    <routestep step="1" x="484.86395" y="344.02573" z="403.30243"/>
		<routestep step="2" x="483.41214" y="351.44702" z="403.14926"/>
		<routestep step="3" x="476.60712" y="361.53198" z="402.2518"/>
		<routestep step="4" x="471.38895" y="369.8956" z="401.9725"/>
		<routestep step="5" x="471.22855" y="372.19894" z="402.57516"/>
		<routestep step="6" x="481.0864" y="384.2167" z="404.04968"/>
		<routestep step="7" x="485.44376" y="391.26352" z="403.028"/>
		<routestep step="8" x="485.42252" y="398.7992" z="403.1279"/>
		<routestep step="9" x="483.5688" y="412.4529" z="400.4512"/>
		<routestep step="10" x="484.23965" y="426.6530" z="398.1594"/>
		<routestep step="11" x="484.42868" y="434.24915" z="397.9744"/>
		<routestep step="12" x="483.40842" y="439.8952" z="398.0240"/>
		<routestep step="13" x="484.57288" y="451.70966" z="398.68048"/>
		<routestep step="14" x="484.44623" y="459.14008" z="398.68338"/>
		<routestep step="15" x="484.73853" y="473.1392" z="398.05243"/>
		<routestep step="16" x="485.46207" y="473.03317" z="398.05637"/>
		<routestep step="17" x="484.96497" y="459.37717" z="398.6549"/>
		<routestep step="18" x="485.01987" y="451.68082" z="398.64496"/>
		<routestep step="19" x="484.2370" y="439.7633" z="397.9749"/>
		<routestep step="20" x="485.13528" y="434.30682" z="397.97775"/>
		<routestep step="21" x="485.01202" y="426.47318" z="398.13452"/>
		<routestep step="22" x="483.9352" y="412.43134" z="400.44397"/>
		<routestep step="23" x="485.68088" y="398.80835" z="403.2146"/>
		<routestep step="24" x="485.81778" y="391.2831" z="403.0559"/>
		<routestep step="25" x="481.42133" y="383.98325" z="404.0169"/>
		<routestep step="26" x="471.61536" y="372.1564" z="402.5874"/>
		<routestep step="27" x="471.6819" y="369.9999" z="402.0181"/>
		<routestep step="28" x="476.89288" y="361.76178" z="402.3025"/>
		<routestep step="29" x="484.0842" y="352.08838" z="403.1911"/>
		<routestep step="30" x="485.36148" y="343.99936" z="403.41293"/>
    </walker_template>
    <walker_template route_id="path_iddreadgion_02_party6_1" pool="2" formation="SQUARE" rows="1,1">
	    <routestep step="1" x="401.4000" y="733.7100" z="400.66763"/>
		<routestep step="2" x="410.5994" y="747.6722" z="396.90564"/>
		<routestep step="3" x="418.6923" y="754.20996" z="394.90958"/>
		<routestep step="4" x="432.41232" y="759.5867" z="393.26074"/>
		<routestep step="5" x="442.07535" y="761.86584" z="392.5179"/>
		<routestep step="6" x="454.25925" y="762.45685" z="391.40918"/>
		<routestep step="7" x="461.07245" y="761.1672" z="390.36334"/>
		<routestep step="8" x="460.7293" y="760.4713" z="390.44968"/>
		<routestep step="9" x="454.51157" y="761.6386" z="391.40875"/>
		<routestep step="10" x="442.37662" y="760.9241" z="392.52252"/>
		<routestep step="11" x="432.8025" y="757.95984" z="393.29144"/>
		<routestep step="12" x="419.35043" y="752.9333" z="394.91135"/>
		<routestep step="13" x="412.33765" y="747.0693" z="396.70438"/>
		<routestep step="14" x="402.20172" y="733.6080" z="400.61346"/>
    </walker_template>
    <walker_template route_id="path_iddreadgion_02_party7_1" pool="2" formation="SQUARE" rows="1,1">
	    <routestep step="1" x="566.82385" y="730.64526" z="401.01303"/>
		<routestep step="2" x="560.1231" y="741.6809" z="397.91684"/>
		<routestep step="3" x="553.1925" y="748.7463" z="395.67053"/>
		<routestep step="4" x="542.59534" y="753.58563" z="393.77692"/>
		<routestep step="5" x="533.1448" y="756.64343" z="393.0194"/>
		<routestep step="6" x="524.15314" y="756.9314" z="392.38388"/>
		<routestep step="7" x="514.16205" y="754.5609" z="391.52365"/>
		<routestep step="8" x="514.4044" y="755.57556" z="391.50977"/>
		<routestep step="9" x="524.1428" y="757.72675" z="392.36465"/>
		<routestep step="10" x="533.65735" y="757.72125" z="393.02658"/>
		<routestep step="11" x="543.3098" y="754.6922" z="393.7854"/>
		<routestep step="12" x="554.04034" y="749.6924" z="395.67297"/>
		<routestep step="13" x="560.97864" y="742.358" z="397.91132"/>
		<routestep step="14" x="567.6256" y="730.5432" z="401.12988"/>
    </walker_template>
    <walker_template route_id="path_iddreadgion_02_party8_1" pool="2" formation="SQUARE" rows="1,1">
	    <routestep step="1" x="483.05777" y="649.69464" z="389.54474"/>
		<routestep step="2" x="483.40646" y="657.41986" z="387.7298"/>
		<routestep step="3" x="483.26468" y="664.8318" z="387.7042"/>
		<routestep step="4" x="483.43536" y="676.41394" z="387.5025"/>
		<routestep step="5" x="483.67737" y="684.5519" z="387.5512"/>
		<routestep step="6" x="483.35843" y="695.1030" z="387.64166"/>
		<routestep step="7" x="483.15536" y="703.9898" z="387.47128"/>
		<routestep step="8" x="483.3222" y="715.3636" z="387.3011"/>
		<routestep step="9" x="483.3430" y="725.80646" z="387.31653"/>
		<routestep step="10" x="486.43655" y="725.81305" z="387.31653"/>
		<routestep step="11" x="486.28833" y="715.92957" z="387.3019"/>
		<routestep step="12" x="485.71732" y="703.9828" z="387.4714"/>
		<routestep step="13" x="485.8266" y="695.1251" z="387.64188"/>
		<routestep step="14" x="486.2061" y="685.08673" z="387.5544"/>
		<routestep step="15" x="486.1307" y="676.3170" z="387.50266"/>
		<routestep step="16" x="485.89526" y="665.17505" z="387.69815"/>
		<routestep step="17" x="485.9158" y="657.5536" z="387.72955"/>
		<routestep step="18" x="485.47607" y="649.2968" z="389.70654"/>
    </walker_template>
    <walker_template route_id="path_iddreadgion_02_shulackworker_1" pool="1">
	    <routestep step="1" x="380.92953" y="706.4537" z="402.22354"/>
		<routestep step="2" x="384.9735" y="703.0088" z="402.22354"/>
		<routestep step="3" x="387.09653" y="699.2531" z="402.21896"/>
		<routestep step="4" x="389.01752" y="694.73737" z="402.20944"/>
		<routestep step="5" x="388.93365" y="690.8158" z="402.22296"/>
		<routestep step="6" x="390.14212" y="684.4377" z="403.19107"/>
		<routestep step="7" x="393.16794" y="673.6092" z="405.23904"/>
		<routestep step="8" x="395.08896" y="662.31586" z="407.7499"/>
		<routestep step="9" x="392.63947" y="652.01385" z="410.68634"/>
		<routestep step="10" x="388.2857" y="644.7698" z="411.73187"/>
		<routestep step="11" x="386.10547" y="637.27814" z="412.83286"/>
		<routestep step="12" x="385.58405" y="632.7335" z="412.18314"/>
		<routestep step="13" x="386.55612" y="625.8942" z="410.66708"/>
		<routestep step="14" x="388.73962" y="621.61816" z="409.93323"/>
		<routestep step="15" x="393.06183" y="616.5722" z="408.4378"/>
		<routestep step="16" x="396.97034" y="611.4481" z="407.82526"/>
		<routestep step="17" x="399.32407" y="603.613" z="408.33536"/>
		<routestep step="18" x="399.7923" y="596.784" z="408.15698"/>
		<routestep step="19" x="399.63297" y="587.9771" z="408.6945"/>
		<routestep step="20" x="394.56445" y="578.4091" z="408.96512"/>
		<routestep step="21" x="390.25528" y="571.93823" z="408.90634"/>
		<routestep step="22" x="383.7375" y="564.4700" z="408.83728"/>
		<routestep step="23" x="375.3767" y="558.6435" z="408.46103"/>
		<routestep step="24" x="366.28647" y="553.1776" z="408.06378"/>
		<routestep step="25" x="361.71927" y="546.6168" z="407.894"/>
		<routestep step="26" x="356.92352" y="541.3612" z="406.9477"/>
		<routestep step="27" x="352.0855" y="532.82556" z="403.5088"/>
		<routestep step="28" x="349.56995" y="523.6431" z="401.76926"/>
		<routestep step="29" x="347.55447" y="517.22394" z="400.59875"/>
		<routestep step="30" x="345.66055" y="511.55502" z="399.4842"/>
		<routestep step="31" x="342.0833" y="502.67227" z="397.89334"/>
		<routestep step="32" x="340.84387" y="494.64185" z="397.91943"/>
		<routestep step="33" x="341.26407" y="482.80582" z="400.24142"/>
		<routestep step="34" x="339.01886" y="473.02625" z="404.1234"/>
		<routestep step="35" x="339.1693" y="463.40826" z="407.20175"/>
		<routestep step="36" x="339.82748" y="454.70526" z="408.8354"/>
		<routestep step="37" x="340.19388" y="445.31213" z="409.2215"/>
		<routestep step="38" x="342.74597" y="437.48758" z="409.48618"/>
		<routestep step="39" x="348.93854" y="430.94446" z="410.10553"/>
		<routestep step="40" x="354.58054" y="423.7833" z="410.562"/>
		<routestep step="41" x="361.44614" y="414.94778" z="410.60043"/>
		<routestep step="42" x="369.99838" y="408.90805" z="410.55923"/>
		<routestep step="43" x="378.04593" y="403.8314" z="410.1895"/>
		<routestep step="44" x="388.67505" y="399.45642" z="410.33862"/>
		<routestep step="45" x="397.55707" y="392.3860" z="410.28516"/>
		<routestep step="46" x="405.9901" y="379.01407" z="408.00497"/>
		<routestep step="47" x="407.3923" y="369.82275" z="405.42706"/>
		<routestep step="48" x="401.4612" y="358.54233" z="402.6849"/>
		<routestep step="49" x="401.58795" y="348.62582" z="403.16464"/>
		<routestep step="50" x="401.9961" y="341.7287" z="402.8301"/>
		<routestep step="51" x="404.05008" y="337.86707" z="402.43774"/>
		<routestep step="52" x="406.85648" y="326.34293" z="402.39594"/>
		<routestep step="53" x="405.53156" y="315.62137" z="404.61545"/>
		<routestep step="54" x="404.69403" y="307.5691" z="408.4995"/>
		<routestep step="55" x="405.80325" y="301.9949" z="409.93298"/>
		<routestep step="56" x="406.68964" y="296.9967" z="409.91776"/>
		<routestep step="57" x="407.8093" y="291.93604" z="409.9955"/>
		<routestep step="58" x="407.9960" y="286.8474" z="409.7311"/>
		<routestep step="59" x="409.26788" y="275.12454" z="409.7311"/>
		<routestep step="60" x="409.24213" y="269.46478" z="409.73108"/>
		<routestep step="61" x="409.24213" y="269.46478" z="409.73108"/>
		<routestep step="62" x="409.59064" y="275.14008" z="409.73337"/>
		<routestep step="63" x="408.3156" y="286.91064" z="409.7311"/>
		<routestep step="64" x="408.15897" y="292.03485" z="410.0122"/>
		<routestep step="65" x="407.10107" y="297.10046" z="409.9196"/>
		<routestep step="66" x="406.01105" y="302.0581" z="409.919"/>
		<routestep step="67" x="404.88846" y="307.59647" z="408.4633"/>
		<routestep step="68" x="405.69476" y="315.60464" z="404.6097"/>
		<routestep step="69" x="407.06473" y="326.39844" z="402.39435"/>
		<routestep step="70" x="404.2126" y="338.0146" z="402.44946"/>
		<routestep step="71" x="402.21082" y="341.87952" z="402.8228"/>
		<routestep step="72" x="401.94208" y="348.7428" z="403.12866"/>
		<routestep step="73" x="401.8779" y="358.3635" z="402.7119"/>
		<routestep step="74" x="407.48782" y="369.76062" z="405.4329"/>
		<routestep step="75" x="406.1404" y="379.1891" z="407.98898"/>
		<routestep step="76" x="397.7340" y="392.6271" z="410.2854"/>
		<routestep step="77" x="388.88617" y="399.72562" z="410.3005"/>
		<routestep step="78" x="378.16446" y="404.05466" z="410.1826"/>
		<routestep step="79" x="370.0948" y="409.07745" z="410.56036"/>
		<routestep step="80" x="361.61093" y="415.06464" z="410.5992"/>
		<routestep step="81" x="354.7680" y="423.9016" z="410.56052"/>
		<routestep step="82" x="349.2013" y="431.1202" z="410.136"/>
		<routestep step="83" x="343.02148" y="437.55307" z="409.46564"/>
		<routestep step="84" x="340.4429" y="445.33932" z="409.21463"/>
		<routestep step="85" x="339.9993" y="454.6901" z="408.8371"/>
		<routestep step="86" x="339.40488" y="463.39" z="407.22784"/>
		<routestep step="87" x="339.28244" y="472.87344" z="404.2205"/>
		<routestep step="88" x="342.17505" y="482.38025" z="400.64853"/>
		<routestep step="89" x="340.97482" y="494.64655" z="397.88715"/>
		<routestep step="90" x="342.22272" y="502.60138" z="397.91037"/>
		<routestep step="91" x="345.7583" y="511.50778" z="399.49426"/>
		<routestep step="92" x="347.88724" y="517.1290" z="400.64224"/>
		<routestep step="93" x="349.8096" y="523.62854" z="401.80756"/>
		<routestep step="94" x="352.21436" y="532.81433" z="403.49908"/>
		<routestep step="95" x="357.3515" y="541.1549" z="406.73215"/>
		<routestep step="96" x="361.95728" y="546.5204" z="407.90735"/>
		<routestep step="97" x="366.5027" y="552.70984" z="408.07584"/>
		<routestep step="98" x="375.49704" y="558.2804" z="408.46472"/>
		<routestep step="99" x="383.78085" y="564.34094" z="408.83932"/>
		<routestep step="100" x="390.3308" y="571.8415" z="408.91248"/>
		<routestep step="101" x="394.60538" y="578.33496" z="408.9743"/>
		<routestep step="102" x="399.72485" y="587.9830" z="408.70218"/>
		<routestep step="103" x="399.93002" y="596.8130" z="408.1612"/>
		<routestep step="104" x="399.47156" y="603.63403" z="408.3343"/>
		<routestep step="105" x="397.18063" y="611.56573" z="407.8535"/>
		<routestep step="106" x="393.17337" y="616.7097" z="408.47342"/>
		<routestep step="107" x="388.90924" y="621.69385" z="409.95044"/>
		<routestep step="108" x="386.6732" y="625.9628" z="410.69458"/>
		<routestep step="109" x="385.62903" y="632.84595" z="412.21844"/>
		<routestep step="110" x="386.21796" y="637.2777" z="412.8578"/>
		<routestep step="111" x="388.39883" y="644.71484" z="411.73428"/>
		<routestep step="112" x="392.71494" y="651.9866" z="410.68933"/>
		<routestep step="113" x="395.21368" y="662.3504" z="407.74335"/>
		<routestep step="114" x="393.42194" y="673.7636" z="405.20654"/>
		<routestep step="115" x="390.35703" y="684.4885" z="403.1820"/>
		<routestep step="116" x="388.9958" y="690.8644" z="402.2190"/>
		<routestep step="117" x="389.2102" y="694.99207" z="402.2099"/>
		<routestep step="118" x="387.39215" y="699.2945" z="402.21896"/>
		<routestep step="119" x="385.11844" y="703.0902" z="402.22354"/>
		<routestep step="120" x="381.02478" y="706.6287" z="402.22354"/>
    </walker_template>
    <walker_template route_id="path_iddreadgion_02_shulackworker_2" pool="1">
	    <routestep step="1" x="381.4363" y="707.49133" z="402.22354"/>
		<routestep step="2" x="385.26285" y="703.6577" z="402.22354"/>
		<routestep step="3" x="387.4267" y="699.7761" z="402.22"/>
		<routestep step="4" x="389.74118" y="695.2386" z="402.21033"/>
		<routestep step="5" x="389.65732" y="691.317" z="402.20755"/>
		<routestep step="6" x="390.86578" y="684.9389" z="403.1067"/>
		<routestep step="7" x="393.8916" y="674.1104" z="405.1319"/>
		<routestep step="8" x="395.81262" y="662.8171" z="407.6404"/>
		<routestep step="9" x="393.36313" y="652.5151" z="410.5467"/>
		<routestep step="10" x="389.00937" y="645.271" z="411.66675"/>
		<routestep step="11" x="386.82913" y="637.77936" z="412.87704"/>
		<routestep step="12" x="386.3077" y="633.23474" z="412.4465"/>
		<routestep step="13" x="387.2798" y="626.39545" z="410.81137"/>
		<routestep step="14" x="389.4633" y="622.1194" z="410.2172"/>
		<routestep step="15" x="393.7855" y="617.0734" z="408.5716"/>
		<routestep step="16" x="397.6940" y="611.94934" z="407.9224"/>
		<routestep step="17" x="400.04773" y="604.1142" z="408.26074"/>
		<routestep step="18" x="400.51596" y="597.2852" z="408.1634"/>
		<routestep step="19" x="400.35663" y="588.47833" z="408.72086"/>
		<routestep step="20" x="395.28812" y="578.91034" z="408.9915"/>
		<routestep step="21" x="390.97894" y="572.43945" z="408.91794"/>
		<routestep step="22" x="384.46115" y="564.9712" z="408.84146"/>
		<routestep step="23" x="376.10037" y="559.1447" z="408.49023"/>
		<routestep step="24" x="367.01013" y="553.67883" z="408.09164"/>
		<routestep step="25" x="362.44293" y="547.11804" z="407.92606"/>
		<routestep step="26" x="357.6472" y="541.8624" z="407.06635"/>
		<routestep step="27" x="352.80917" y="533.3268" z="403.63965"/>
		<routestep step="28" x="350.2936" y="524.14435" z="401.9556"/>
		<routestep step="29" x="348.27814" y="517.72516" z="400.7851"/>
		<routestep step="30" x="346.38422" y="512.0563" z="399.68396"/>
		<routestep step="31" x="342.80698" y="503.1735" z="397.9666"/>
		<routestep step="32" x="341.56754" y="495.14307" z="397.79688"/>
		<routestep step="33" x="341.98773" y="483.30704" z="400.08264"/>
		<routestep step="34" x="339.74252" y="473.52747" z="403.96512"/>
		<routestep step="35" x="339.89297" y="463.9095" z="407.13712"/>
		<routestep step="36" x="340.55115" y="455.20648" z="408.7952"/>
		<routestep step="37" x="340.91754" y="445.81335" z="409.19092"/>
		<routestep step="38" x="343.46964" y="437.9888" z="409.4166"/>
		<routestep step="39" x="349.6622" y="431.44568" z="410.20706"/>
		<routestep step="40" x="355.3042" y="424.28452" z="410.55594"/>
		<routestep step="41" x="362.1698" y="415.4490" z="410.59512"/>
		<routestep step="42" x="370.72205" y="409.40927" z="410.55542"/>
		<routestep step="43" x="378.7696" y="404.3326" z="410.20135"/>
		<routestep step="44" x="389.3987" y="399.95764" z="410.26077"/>
		<routestep step="45" x="398.28073" y="392.8872" z="410.2705"/>
		<routestep step="46" x="406.71378" y="379.5153" z="407.89542"/>
		<routestep step="47" x="408.11597" y="370.32397" z="405.72556"/>
		<routestep step="48" x="402.18488" y="359.04355" z="402.90594"/>
		<routestep step="49" x="402.3116" y="349.12704" z="403.06158"/>
		<routestep step="50" x="402.71976" y="342.22992" z="402.80545"/>
		<routestep step="51" x="404.77374" y="338.3683" z="402.4775"/>
		<routestep step="52" x="407.58014" y="326.84415" z="402.38187"/>
		<routestep step="53" x="406.25522" y="316.1226" z="404.44824"/>
		<routestep step="54" x="405.4177" y="308.0703" z="408.20834"/>
		<routestep step="55" x="406.52692" y="302.49612" z="409.87698"/>
		<routestep step="56" x="407.4133" y="297.49792" z="409.91562"/>
		<routestep step="57" x="408.48682" y="292.89474" z="410.05447"/>
		<routestep step="58" x="409.0507" y="287.14026" z="409.7311"/>
		<routestep step="59" x="410.57828" y="275.3764" z="409.7311"/>
		<routestep step="60" x="410.40906" y="270.06512" z="409.73108"/>
		<routestep step="61" x="410.74005" y="270.07425" z="409.73108"/>
		<routestep step="62" x="410.90103" y="275.39194" z="409.7311"/>
		<routestep step="63" x="409.3703" y="287.2035" z="409.7311"/>
		<routestep step="64" x="408.8365" y="292.99356" z="410.07364"/>
		<routestep step="65" x="407.82474" y="297.60168" z="409.91745"/>
		<routestep step="66" x="406.7347" y="302.55933" z="409.85858"/>
		<routestep step="67" x="405.61212" y="308.0977" z="408.21765"/>
		<routestep step="68" x="406.41843" y="316.10587" z="404.45862"/>
		<routestep step="69" x="407.7884" y="326.89966" z="402.38028"/>
		<routestep step="70" x="404.93625" y="338.5158" z="402.48923"/>
		<routestep step="71" x="402.93448" y="342.38074" z="402.79816"/>
		<routestep step="72" x="402.66574" y="349.24402" z="403.01233"/>
		<routestep step="73" x="402.60156" y="358.86472" z="403.08954"/>
		<routestep step="74" x="408.2115" y="370.26184" z="405.72943"/>
		<routestep step="75" x="406.86407" y="379.6903" z="407.86783"/>
		<routestep step="76" x="398.45767" y="393.12833" z="410.27576"/>
		<routestep step="77" x="389.60983" y="400.22684" z="410.21854"/>
		<routestep step="78" x="378.88812" y="404.55588" z="410.21802"/>
		<routestep step="79" x="370.81845" y="409.57867" z="410.555"/>
		<routestep step="80" x="362.3346" y="415.56586" z="410.5939"/>
		<routestep step="81" x="355.49167" y="424.40283" z="410.55444"/>
		<routestep step="82" x="349.92496" y="431.62143" z="410.2482"/>
		<routestep step="83" x="343.74515" y="438.0543" z="409.3961"/>
		<routestep step="84" x="341.16656" y="445.84055" z="409.1818"/>
		<routestep step="85" x="340.72296" y="455.1913" z="408.79688"/>
		<routestep step="86" x="340.12854" y="463.89124" z="407.1632"/>
		<routestep step="87" x="340.0061" y="473.37466" z="404.0622"/>
		<routestep step="88" x="342.8987" y="482.88147" z="400.76038"/>
		<routestep step="89" x="341.6985" y="495.14777" z="397.78424"/>
		<routestep step="90" x="342.94638" y="503.1026" z="397.98364"/>
		<routestep step="91" x="346.48196" y="512.00903" z="399.68927"/>
		<routestep step="92" x="348.6109" y="517.63025" z="400.82858"/>
		<routestep step="93" x="350.53326" y="524.12976" z="401.99402"/>
		<routestep step="94" x="352.93802" y="533.31555" z="403.6423"/>
		<routestep step="95" x="358.07516" y="541.6561" z="407.06473"/>
		<routestep step="96" x="362.68094" y="547.0216" z="407.9394"/>
		<routestep step="97" x="367.22635" y="553.21106" z="408.10788"/>
		<routestep step="98" x="376.2207" y="558.7816" z="408.49393"/>
		<routestep step="99" x="384.50452" y="564.84216" z="408.84225"/>
		<routestep step="100" x="391.05447" y="572.3427" z="408.92093"/>
		<routestep step="101" x="395.32904" y="578.8362" z="409.0007"/>
		<routestep step="102" x="400.44852" y="588.4842" z="408.72858"/>
		<routestep step="103" x="400.6537" y="597.3142" z="408.1676"/>
		<routestep step="104" x="400.19522" y="604.13525" z="408.257"/>
		<routestep step="105" x="397.9043" y="612.06696" z="407.95062"/>
		<routestep step="106" x="393.89703" y="617.21094" z="408.61658"/>
		<routestep step="107" x="389.6329" y="622.19507" z="410.32672"/>
		<routestep step="108" x="387.39685" y="626.46405" z="410.8864"/>
		<routestep step="109" x="386.3527" y="633.34717" z="412.48184"/>
		<routestep step="110" x="386.94162" y="637.77893" z="412.88974"/>
		<routestep step="111" x="389.1225" y="645.21606" z="411.66913"/>
		<routestep step="112" x="393.4386" y="652.4878" z="410.5497"/>
		<routestep step="113" x="395.93735" y="662.8516" z="407.63388"/>
		<routestep step="114" x="394.1456" y="674.26483" z="405.0994"/>
		<routestep step="115" x="391.0807" y="684.98975" z="403.09766"/>
		<routestep step="116" x="389.71945" y="691.3656" z="402.20755"/>
		<routestep step="117" x="389.93387" y="695.4933" z="402.21082"/>
		<routestep step="118" x="387.72232" y="699.8175" z="402.21997"/>
		<routestep step="119" x="385.40778" y="703.73914" z="402.22354"/>
		<routestep step="120" x="381.53156" y="707.6664" z="402.22354"/>
    </walker_template>
    <walker_template route_id="path_iddreadgion_02_shulackworker_3" pool="1">
	    <routestep step="1" x="565.4498" y="701.52576" z="402.2126"/>
		<routestep step="2" x="568.3738" y="700.6767" z="402.2170"/>
		<routestep step="3" x="575.6624" y="698.0607" z="402.2147"/>
		<routestep step="4" x="579.5760" y="694.6363" z="402.2089"/>
		<routestep step="5" x="580.1975" y="691.45215" z="402.20755"/>
		<routestep step="6" x="579.7252" y="685.07404" z="403.02924"/>
		<routestep step="7" x="577.8179" y="674.24554" z="404.99023"/>
		<routestep step="8" x="573.5432" y="662.9522" z="407.53912"/>
		<routestep step="9" x="577.28937" y="652.6502" z="410.45633"/>
		<routestep step="10" x="580.5170" y="645.4061" z="411.60678"/>
		<routestep step="11" x="584.4965" y="637.9145" z="412.91992"/>
		<routestep step="12" x="585.4505" y="633.3699" z="412.27222"/>
		<routestep step="13" x="584.8147" y="626.5306" z="410.5609"/>
		<routestep step="14" x="583.15045" y="622.2545" z="409.90002"/>
		<routestep step="15" x="577.7118" y="617.20856" z="408.54645"/>
		<routestep step="16" x="572.9050" y="612.0845" z="407.78824"/>
		<routestep step="17" x="571.1618" y="604.2493" z="408.17874"/>
		<routestep step="18" x="571.0355" y="597.42035" z="408.0420"/>
		<routestep step="19" x="571.0805" y="588.61346" z="408.53485"/>
		<routestep step="20" x="570.7493" y="579.0455" z="408.9301"/>
		<routestep step="21" x="579.92737" y="572.5746" z="408.84863"/>
		<routestep step="22" x="587.2330" y="565.1063" z="408.75323"/>
		<routestep step="23" x="594.49994" y="559.27985" z="408.41287"/>
		<routestep step="24" x="602.9477" y="553.81396" z="408.03934"/>
		<routestep step="25" x="607.93976" y="547.2532" z="407.8506"/>
		<routestep step="26" x="609.87213" y="541.99756" z="407.40698"/>
		<routestep step="27" x="617.5451" y="533.4619" z="403.5976"/>
		<routestep step="28" x="620.8315" y="524.2795" z="401.7207"/>
		<routestep step="29" x="624.53827" y="517.8603" z="400.35913"/>
		<routestep step="30" x="626.28796" y="512.1914" z="399.20834"/>
		<routestep step="31" x="629.43463" y="503.30862" z="397.71494"/>
		<routestep step="32" x="630.6994" y="495.2782" z="398.17712"/>
		<routestep step="33" x="632.56976" y="483.44217" z="400.05637"/>
		<routestep step="34" x="633.0695" y="473.6626" z="403.62576"/>
		<routestep step="35" x="631.1237" y="464.04462" z="406.97552"/>
		<routestep step="36" x="630.9690" y="455.3416" z="408.72586"/>
		<routestep step="37" x="630.24475" y="445.9485" z="409.14175"/>
		<routestep step="38" x="629.65094" y="438.12393" z="409.4677"/>
		<routestep step="39" x="627.7624" y="431.5808" z="409.71844"/>
		<routestep step="40" x="623.4589" y="424.41965" z="410.0817"/>
		<routestep step="41" x="616.2121" y="415.58414" z="410.5634"/>
		<routestep step="42" x="610.5543" y="409.5444" z="410.55988"/>
		<routestep step="43" x="595.9573" y="404.46774" z="410.1960"/>
		<routestep step="44" x="582.8554" y="400.09277" z="410.26245"/>
		<routestep step="45" x="573.54834" y="393.02234" z="410.3964"/>
		<routestep step="46" x="563.6753" y="379.65042" z="407.8885"/>
		<routestep step="47" x="562.1415" y="370.4591" z="405.6261"/>
		<routestep step="48" x="568.90765" y="359.17868" z="402.87762"/>
		<routestep step="49" x="569.9532" y="349.26218" z="403.23044"/>
		<routestep step="50" x="570.2547" y="342.36505" z="403.1177"/>
		<routestep step="51" x="568.9459" y="338.50342" z="402.5645"/>
		<routestep step="52" x="563.39764" y="326.97928" z="402.37823"/>
		<routestep step="53" x="565.0313" y="316.25772" z="404.46683"/>
		<routestep step="54" x="565.38745" y="308.20544" z="408.18597"/>
		<routestep step="55" x="564.58026" y="302.63126" z="409.9124"/>
		<routestep step="56" x="562.3463" y="298.91852" z="410.07745"/>
		<routestep step="57" x="561.5698" y="293.1427" z="409.94394"/>
		<routestep step="58" x="561.09344" y="284.95264" z="409.7311"/>
		<routestep step="59" x="562.80304" y="275.7609" z="409.7311"/>
		<routestep step="60" x="565.32916" y="270.10114" z="409.9499"/>
		<routestep step="61" x="565.6602" y="270.11026" z="409.93488"/>
		<routestep step="62" x="563.1258" y="275.77643" z="409.7311"/>
		<routestep step="63" x="561.4130" y="285.01587" z="409.7311"/>
		<routestep step="64" x="561.9195" y="293.24152" z="409.95712"/>
		<routestep step="65" x="562.7578" y="299.02228" z="410.10132"/>
		<routestep step="66" x="564.788" y="302.69446" z="409.91864"/>
		<routestep step="67" x="565.5819" y="308.23282" z="408.19778"/>
		<routestep step="68" x="565.1945" y="316.241" z="404.50287"/>
		<routestep step="69" x="563.6059" y="327.0348" z="402.37674"/>
		<routestep step="70" x="569.1084" y="338.65094" z="402.59192"/>
		<routestep step="71" x="570.4694" y="342.51587" z="403.15274"/>
		<routestep step="72" x="570.3073" y="349.37915" z="403.2060"/>
		<routestep step="73" x="569.32434" y="358.99985" z="403.01224"/>
		<routestep step="74" x="561.9643" y="370.39697" z="405.6507"/>
		<routestep step="75" x="563.82556" y="379.82544" z="407.92093"/>
		<routestep step="76" x="573.72534" y="393.26346" z="410.43088"/>
		<routestep step="77" x="583.06647" y="400.36197" z="410.23846"/>
		<routestep step="78" x="596.0758" y="404.691" z="410.18515"/>
		<routestep step="79" x="610.6507" y="409.7138" z="410.56052"/>
		<routestep step="80" x="616.3769" y="415.701" z="410.56342"/>
		<routestep step="81" x="623.64636" y="424.53796" z="410.0528"/>
		<routestep step="82" x="628.0252" y="431.75656" z="409.71503"/>
		<routestep step="83" x="629.92645" y="438.18942" z="409.46924"/>
		<routestep step="84" x="630.4938" y="445.97568" z="409.1445"/>
		<routestep step="85" x="631.1408" y="455.32645" z="408.7267"/>
		<routestep step="86" x="631.35925" y="464.02637" z="406.9547"/>
		<routestep step="87" x="633.3331" y="473.5098" z="403.6906"/>
		<routestep step="88" x="633.4808" y="483.0166" z="400.24582"/>
		<routestep step="89" x="630.8303" y="495.2829" z="398.20856"/>
		<routestep step="90" x="629.57404" y="503.23773" z="397.73022"/>
		<routestep step="91" x="626.38574" y="512.14417" z="399.1876"/>
		<routestep step="92" x="624.87103" y="517.7654" z="400.35315"/>
		<routestep step="93" x="621.0711" y="524.2649" z="401.67862"/>
		<routestep step="94" x="617.6740" y="533.4507" z="403.59308"/>
		<routestep step="95" x="610.3001" y="541.79126" z="407.32877"/>
		<routestep step="96" x="608.1778" y="547.15674" z="407.83762"/>
		<routestep step="97" x="603.16394" y="553.3462" z="408.0324"/>
		<routestep step="98" x="594.62024" y="558.91675" z="408.40424"/>
		<routestep step="99" x="587.27637" y="564.9773" z="408.75296"/>
		<routestep step="100" x="580.0029" y="572.47784" z="408.8428"/>
		<routestep step="101" x="570.7902" y="578.9713" z="408.92697"/>
		<routestep step="102" x="571.1724" y="588.6193" z="408.52628"/>
		<routestep step="103" x="571.1733" y="597.44934" z="408.0352"/>
		<routestep step="104" x="571.3093" y="604.2704" z="408.17285"/>
		<routestep step="105" x="573.1153" y="612.2021" z="407.75998"/>
		<routestep step="106" x="577.8233" y="617.34607" z="408.58707"/>
		<routestep step="107" x="583.3200" y="622.3302" z="409.90073"/>
		<routestep step="108" x="584.93176" y="626.5992" z="410.56088"/>
		<routestep step="109" x="585.49554" y="633.4823" z="412.31"/>
		<routestep step="110" x="584.60895" y="637.91406" z="412.9521"/>
		<routestep step="111" x="580.6302" y="645.3512" z="411.61475"/>
		<routestep step="112" x="577.36487" y="652.6229" z="410.46545"/>
		<routestep step="113" x="573.6679" y="662.98676" z="407.52515"/>
		<routestep step="114" x="578.0719" y="674.39996" z="404.95026"/>
		<routestep step="115" x="579.9401" y="685.1249" z="403.0217"/>
		<routestep step="116" x="580.25964" y="691.50073" z="402.20755"/>
		<routestep step="117" x="579.76874" y="694.8910" z="402.20947"/>
		<routestep step="118" x="575.9580" y="698.1021" z="402.21487"/>
		<routestep step="119" x="568.5187" y="700.7581" z="402.21725"/>
		<routestep step="120" x="565.5451" y="701.7008" z="402.2131"/>
    </walker_template>
    <walker_template route_id="path_iddreadgion_02_shulackworker_4" pool="1">
	    <routestep step="1" x="564.98895" y="699.97675" z="402.20923"/>
		<routestep step="2" x="568.6036" y="699.57886" z="402.2150"/>
		<routestep step="3" x="575.5856" y="697.74426" z="402.21652"/>
		<routestep step="4" x="578.92865" y="694.4363" z="402.2083"/>
		<routestep step="5" x="580.14185" y="690.8494" z="402.20755"/>
		<routestep step="6" x="579.66956" y="684.4713" z="403.12744"/>
		<routestep step="7" x="577.7622" y="673.6428" z="405.13388"/>
		<routestep step="8" x="573.48755" y="662.3495" z="407.67908"/>
		<routestep step="9" x="577.2337" y="652.0475" z="410.59253"/>
		<routestep step="10" x="580.46136" y="644.8034" z="411.66235"/>
		<routestep step="11" x="584.44086" y="637.31177" z="412.8679"/>
		<routestep step="12" x="585.39484" y="632.76715" z="412.09485"/>
		<routestep step="13" x="584.75903" y="625.92786" z="410.44672"/>
		<routestep step="14" x="583.0948" y="621.6518" z="409.8093"/>
		<routestep step="15" x="577.6561" y="616.60583" z="408.4646"/>
		<routestep step="16" x="572.84937" y="611.48175" z="407.7958"/>
		<routestep step="17" x="571.10614" y="603.6466" z="408.2793"/>
		<routestep step="18" x="570.97986" y="596.8176" z="408.07132"/>
		<routestep step="19" x="571.02484" y="588.01074" z="408.58508"/>
		<routestep step="20" x="570.69366" y="578.44275" z="408.94913"/>
		<routestep step="21" x="579.8717" y="571.97186" z="408.84628"/>
		<routestep step="22" x="587.1773" y="564.5036" z="408.75647"/>
		<routestep step="23" x="594.4443" y="558.6771" z="408.4104"/>
		<routestep step="24" x="602.892" y="553.21124" z="408.04584"/>
		<routestep step="25" x="607.8841" y="546.65045" z="407.85828"/>
		<routestep step="26" x="609.81647" y="541.39484" z="407.37274"/>
		<routestep step="27" x="617.48944" y="532.8592" z="403.4113"/>
		<routestep step="28" x="620.7758" y="523.67676" z="401.65186"/>
		<routestep step="29" x="624.4826" y="517.25757" z="400.21967"/>
		<routestep step="30" x="626.2323" y="511.58865" z="399.12863"/>
		<routestep step="31" x="629.37897" y="502.7059" z="397.75244"/>
		<routestep step="32" x="630.64374" y="494.67548" z="398.2095"/>
		<routestep step="33" x="632.5141" y="482.83945" z="400.16733"/>
		<routestep step="34" x="633.01385" y="473.05988" z="403.91223"/>
		<routestep step="35" x="631.06805" y="463.4419" z="407.13968"/>
		<routestep step="36" x="630.9133" y="454.7389" z="408.77652"/>
		<routestep step="37" x="630.1891" y="445.34576" z="409.1667"/>
		<routestep step="38" x="629.5953" y="437.5212" z="409.49268"/>
		<routestep step="39" x="627.7067" y="430.9781" z="409.7434"/>
		<routestep step="40" x="623.40326" y="423.81693" z="410.1194"/>
		<routestep step="41" x="616.15643" y="414.9814" z="410.56674"/>
		<routestep step="42" x="610.49866" y="408.94168" z="410.55917"/>
		<routestep step="43" x="595.9016" y="403.86502" z="410.26367"/>
		<routestep step="44" x="582.79974" y="399.49005" z="410.3301"/>
		<routestep step="45" x="573.4927" y="392.41962" z="410.39288"/>
		<routestep step="46" x="563.6196" y="379.0477" z="407.85953"/>
		<routestep step="47" x="562.0858" y="369.85638" z="405.48233"/>
		<routestep step="48" x="568.852" y="358.57596" z="402.74268"/>
		<routestep step="49" x="569.8975" y="348.65945" z="403.27277"/>
		<routestep step="50" x="570.19904" y="341.76233" z="403.02884"/>
		<routestep step="51" x="568.89026" y="337.9007" z="402.47736"/>
		<routestep step="52" x="563.342" y="326.37656" z="402.3950"/>
		<routestep step="53" x="564.97565" y="315.655" z="404.6407"/>
		<routestep step="54" x="565.3318" y="307.60272" z="408.45264"/>
		<routestep step="55" x="564.5246" y="302.02853" z="409.93198"/>
		<routestep step="56" x="562.29065" y="298.3158" z="410.07294"/>
		<routestep step="57" x="561.51416" y="292.53998" z="409.95746"/>
		<routestep step="58" x="561.0378" y="284.3499" z="409.7311"/>
		<routestep step="59" x="562.7474" y="275.15817" z="409.7311"/>
		<routestep step="60" x="565.2735" y="269.4984" z="409.94156"/>
		<routestep step="61" x="565.60455" y="269.50754" z="409.9286"/>
		<routestep step="62" x="563.0701" y="275.1737" z="409.7311"/>
		<routestep step="63" x="561.35736" y="284.41315" z="409.7311"/>
		<routestep step="64" x="561.86383" y="292.6388" z="409.97165"/>
		<routestep step="65" x="562.70215" y="298.41956" z="410.0961"/>
		<routestep step="66" x="564.73236" y="302.09174" z="409.9407"/>
		<routestep step="67" x="565.52625" y="307.6301" z="408.45996"/>
		<routestep step="68" x="565.13885" y="315.63828" z="404.67676"/>
		<routestep step="69" x="563.55023" y="326.43207" z="402.3935"/>
		<routestep step="70" x="569.05273" y="338.04822" z="402.5048"/>
		<routestep step="71" x="570.41376" y="341.91315" z="403.07605"/>
		<routestep step="72" x="570.25165" y="348.77643" z="403.30298"/>
		<routestep step="73" x="569.2687" y="358.39713" z="402.87225"/>
		<routestep step="74" x="561.9086" y="369.79425" z="405.50693"/>
		<routestep step="75" x="563.7699" y="379.22272" z="407.8923"/>
		<routestep step="76" x="573.6697" y="392.66074" z="410.41846"/>
		<routestep step="77" x="583.0108" y="399.75925" z="410.30612"/>
		<routestep step="78" x="596.02014" y="404.0883" z="410.2426"/>
		<routestep step="79" x="610.59503" y="409.11108" z="410.55984"/>
		<routestep step="80" x="616.3212" y="415.09827" z="410.56677"/>
		<routestep step="81" x="623.5907" y="423.93524" z="410.08936"/>
		<routestep step="82" x="627.96954" y="431.15384" z="409.74"/>
		<routestep step="83" x="629.8708" y="437.5867" z="409.49417"/>
		<routestep step="84" x="630.4381" y="445.37296" z="409.16943"/>
		<routestep step="85" x="631.08514" y="454.72372" z="408.77737"/>
		<routestep step="86" x="631.3036" y="463.42365" z="407.1203"/>
		<routestep step="87" x="633.27747" y="472.90707" z="403.97708"/>
		<routestep step="88" x="633.4251" y="482.41388" z="400.3562"/>
		<routestep step="89" x="630.77466" y="494.68018" z="398.23965"/>
		<routestep step="90" x="629.5184" y="502.6350" z="397.7637"/>
		<routestep step="91" x="626.3301" y="511.5414" z="399.11224"/>
		<routestep step="92" x="624.81537" y="517.16266" z="400.21368"/>
		<routestep step="93" x="621.01544" y="523.6622" z="401.6098"/>
		<routestep step="94" x="617.61835" y="532.84796" z="403.41586"/>
		<routestep step="95" x="610.24445" y="541.18854" z="407.2901"/>
		<routestep step="96" x="608.12213" y="546.554" z="407.847"/>
		<routestep step="97" x="603.1083" y="552.74347" z="408.0397"/>
		<routestep step="98" x="594.5646" y="558.314" z="408.40482"/>
		<routestep step="99" x="587.2207" y="564.3746" z="408.7562"/>
		<routestep step="100" x="579.94727" y="571.8751" z="408.847"/>
		<routestep step="101" x="570.73456" y="578.3686" z="408.9503"/>
		<routestep step="102" x="571.11676" y="588.0166" z="408.5765"/>
		<routestep step="103" x="571.1176" y="596.8466" z="408.0645"/>
		<routestep step="104" x="571.25366" y="603.66766" z="408.2734"/>
		<routestep step="105" x="573.05963" y="611.59937" z="407.76755"/>
		<routestep step="106" x="577.76764" y="616.74335" z="408.49518"/>
		<routestep step="107" x="583.26434" y="621.7275" z="409.84857"/>
		<routestep step="108" x="584.8761" y="625.99646" z="410.4641"/>
		<routestep step="109" x="585.4399" y="632.8796" z="412.13263"/>
		<routestep step="110" x="584.5533" y="637.31134" z="412.8956"/>
		<routestep step="111" x="580.5745" y="644.7485" z="411.67032"/>
		<routestep step="112" x="577.3092" y="652.0202" z="410.6028"/>
		<routestep step="113" x="573.61224" y="662.38403" z="407.6692"/>
		<routestep step="114" x="578.01624" y="673.79724" z="405.09293"/>
		<routestep step="115" x="579.88446" y="684.52216" z="403.1199"/>
		<routestep step="116" x="580.2040" y="690.8980" z="402.20755"/>
		<routestep step="117" x="579.1214" y="694.6910" z="402.2089"/>
		<routestep step="118" x="575.88116" y="697.78564" z="402.21423"/>
		<routestep step="119" x="568.7485" y="699.6603" z="402.2152"/>
		<routestep step="120" x="565.0842" y="700.1518" z="402.2096"/>
    </walker_template>
    <walker_template route_id="path_iddreadgion_02_shulackworker_5" pool="1">
	    <routestep step="1" x="405.4400" y="711.3100" z="402.34213"/>
		<routestep step="2" x="403.3992" y="708.2579" z="402.23563"/>
		<routestep step="3" x="401.74753" y="704.4317" z="402.22354"/>
		<routestep step="4" x="398.7796" y="701.9083" z="402.22052"/>
		<routestep step="5" x="393.8315" y="698.4248" z="402.2156"/>
		<routestep step="6" x="391.1432" y="694.72943" z="402.20895"/>
		<routestep step="7" x="391.05646" y="691.0647" z="402.21445"/>
		<routestep step="8" x="391.82483" y="685.35284" z="403.03577"/>
		<routestep step="9" x="392.52917" y="680.92993" z="403.7361"/>
		<routestep step="10" x="394.37405" y="674.1503" z="405.13046"/>
		<routestep step="11" x="396.08905" y="662.78986" z="407.6506"/>
		<routestep step="12" x="393.5679" y="652.5507" z="410.5314"/>
		<routestep step="13" x="388.6619" y="645.43176" z="411.6601"/>
		<routestep step="14" x="386.48395" y="638.1836" z="412.78357"/>
		<routestep step="15" x="385.72855" y="633.1164" z="412.3017"/>
		<routestep step="16" x="386.84363" y="626.08234" z="410.73688"/>
		<routestep step="17" x="389.2144" y="621.95013" z="410.0153"/>
		<routestep step="18" x="393.42172" y="616.9202" z="408.52628"/>
		<routestep step="19" x="397.27228" y="611.7397" z="407.87054"/>
		<routestep step="20" x="399.37698" y="604.0299" z="408.26727"/>
		<routestep step="21" x="399.9533" y="596.7606" z="408.1645"/>
		<routestep step="22" x="399.91895" y="588.3457" z="408.69208"/>
		<routestep step="23" x="395.46744" y="579.0720" z="408.9952"/>
		<routestep step="24" x="391.22076" y="572.11426" z="408.9350"/>
		<routestep step="25" x="384.4975" y="564.6735" z="408.84314"/>
		<routestep step="26" x="376.1306" y="558.6034" z="408.4900"/>
		<routestep step="27" x="367.18167" y="552.5784" z="408.11237"/>
		<routestep step="28" x="362.7590" y="547.3635" z="407.93976"/>
		<routestep step="29" x="358.13348" y="541.75195" z="407.0985"/>
		<routestep step="30" x="353.4825" y="533.355" z="403.77792"/>
		<routestep step="31" x="350.84515" y="523.8269" z="402.01373"/>
		<routestep step="32" x="348.90762" y="517.4921" z="400.8610"/>
		<routestep step="33" x="346.79132" y="511.73886" z="399.7042"/>
		<routestep step="34" x="343.31693" y="502.95642" z="398.02823"/>
		<routestep step="35" x="341.8412" y="495.16953" z="397.7727"/>
		<routestep step="36" x="344.83997" y="493.129" z="397.05066"/>
		<routestep step="37" x="347.4405" y="492.5464" z="396.18454"/>
		<routestep step="38" x="354.19843" y="492.0003" z="394.26025"/>
		<routestep step="39" x="359.3576" y="491.60803" z="394.37476"/>
		<routestep step="40" x="366.58362" y="490.8928" z="394.6477"/>
		<routestep step="41" x="368.9105" y="491.27008" z="394.51486"/>
		<routestep step="42" x="376.50092" y="492.42117" z="393.28656"/>
		<routestep step="43" x="382.08545" y="492.76385" z="393.47275"/>
		<routestep step="44" x="382.57632" y="486.54102" z="393.49396"/>
		<routestep step="45" x="383.45184" y="480.41504" z="393.3259"/>
		<routestep step="46" x="383.6344" y="480.42294" z="393.33487"/>
		<routestep step="47" x="382.75122" y="486.65015" z="393.50027"/>
		<routestep step="48" x="382.2251" y="492.85034" z="393.47418"/>
		<routestep step="49" x="376.39133" y="492.45078" z="393.2853"/>
		<routestep step="50" x="368.8827" y="491.45038" z="394.49756"/>
		<routestep step="51" x="366.4662" y="491.04202" z="394.6265"/>
		<routestep step="52" x="359.29065" y="491.84903" z="394.3445"/>
		<routestep step="53" x="354.22803" y="492.21884" z="394.2121"/>
		<routestep step="54" x="347.44553" y="492.79013" z="396.2177"/>
		<routestep step="55" x="344.4663" y="493.5770" z="397.16345"/>
		<routestep step="56" x="341.9751" y="495.2090" z="397.76248"/>
		<routestep step="57" x="343.41284" y="502.90793" z="398.04144"/>
		<routestep step="58" x="346.83777" y="511.70572" z="399.71005"/>
		<routestep step="59" x="348.82132" y="517.66724" z="400.86868"/>
		<routestep step="60" x="350.95822" y="523.82697" z="402.03467"/>
		<routestep step="61" x="353.5640" y="533.3319" z="403.79077"/>
		<routestep step="62" x="358.17865" y="541.7376" z="407.10037"/>
		<routestep step="63" x="362.68942" y="547.0619" z="407.9394"/>
		<routestep step="64" x="367.23257" y="552.4755" z="408.11612"/>
		<routestep step="65" x="376.17984" y="558.5671" z="408.4918"/>
		<routestep step="66" x="384.5107" y="564.6238" z="408.84344"/>
		<routestep step="67" x="391.29095" y="572.1007" z="408.938"/>
		<routestep step="68" x="395.52213" y="578.6826" z="409.02936"/>
		<routestep step="69" x="399.95142" y="588.3401" z="408.69537"/>
		<routestep step="70" x="400.01993" y="596.7868" z="408.16595"/>
		<routestep step="71" x="399.44257" y="604.0563" z="408.264"/>
		<routestep step="72" x="397.1893" y="611.7057" z="407.8546"/>
		<routestep step="73" x="393.32166" y="616.87463" z="408.51584"/>
		<routestep step="74" x="389.1731" y="621.91406" z="410.0056"/>
		<routestep step="75" x="386.87912" y="626.0706" z="410.73578"/>
		<routestep step="76" x="385.7506" y="633.0921" z="412.30048"/>
		<routestep step="77" x="386.5024" y="638.16235" z="412.78452"/>
		<routestep step="78" x="388.6605" y="645.3608" z="411.6668"/>
		<routestep step="79" x="393.5567" y="652.51917" z="410.53806"/>
		<routestep step="80" x="396.13544" y="662.7991" z="407.64902"/>
		<routestep step="81" x="394.44293" y="674.14746" z="405.1323"/>
		<routestep step="82" x="392.59714" y="680.93445" z="403.73575"/>
		<routestep step="83" x="391.88898" y="685.37036" z="403.03268"/>
		<routestep step="84" x="391.10928" y="691.0572" z="402.2152"/>
		<routestep step="85" x="391.17932" y="694.70294" z="402.2089"/>
		<routestep step="86" x="393.83215" y="698.4136" z="402.2156"/>
		<routestep step="87" x="398.80606" y="701.86383" z="402.22043"/>
		<routestep step="88" x="401.7158" y="704.384" z="402.22354"/>
		<routestep step="89" x="403.42444" y="708.2396" z="402.2373"/>
		<routestep step="90" x="405.5419" y="711.3412" z="402.34497"/>
    </walker_template>
    <walker_template route_id="path_iddreadgion_02_shulackworker_6" pool="1">
	    <routestep step="1" x="404.4000" y="713.4300" z="402.2708"/>
		<routestep step="2" x="402.94788" y="709.01544" z="402.2514"/>
		<routestep step="3" x="401.25522" y="705.07916" z="402.22354"/>
		<routestep step="4" x="398.6647" y="701.98627" z="402.2207"/>
		<routestep step="5" x="393.7166" y="698.50275" z="402.21582"/>
		<routestep step="6" x="391.0283" y="694.8074" z="402.20914"/>
		<routestep step="7" x="390.94156" y="691.14264" z="402.2127"/>
		<routestep step="8" x="391.70993" y="685.4308" z="403.02344"/>
		<routestep step="9" x="392.41428" y="681.0079" z="403.72418"/>
		<routestep step="10" x="394.25916" y="674.2283" z="405.1100"/>
		<routestep step="11" x="395.97415" y="662.8678" z="407.63052"/>
		<routestep step="12" x="393.4530" y="652.62866" z="410.51804"/>
		<routestep step="13" x="388.5470" y="645.5097" z="411.65555"/>
		<routestep step="14" x="386.36905" y="638.26154" z="412.75507"/>
		<routestep step="15" x="385.61365" y="633.19434" z="412.2966"/>
		<routestep step="16" x="386.72873" y="626.1603" z="410.74066"/>
		<routestep step="17" x="389.0995" y="622.0281" z="410.032"/>
		<routestep step="18" x="393.30682" y="616.99817" z="408.55045"/>
		<routestep step="19" x="397.15738" y="611.8176" z="407.8534"/>
		<routestep step="20" x="399.2621" y="604.10785" z="408.25253"/>
		<routestep step="21" x="399.8384" y="596.83856" z="408.15637"/>
		<routestep step="22" x="399.80405" y="588.42365" z="408.67606"/>
		<routestep step="23" x="395.35254" y="579.14996" z="408.9792"/>
		<routestep step="24" x="391.10587" y="572.1922" z="408.9281"/>
		<routestep step="25" x="384.3826" y="564.75146" z="408.84247"/>
		<routestep step="26" x="376.01572" y="558.68134" z="408.48584"/>
		<routestep step="27" x="367.06677" y="552.6564" z="408.1056"/>
		<routestep step="28" x="362.6441" y="547.44147" z="407.93298"/>
		<routestep step="29" x="358.0186" y="541.8299" z="407.10513"/>
		<routestep step="30" x="353.3676" y="533.4329" z="403.7715"/>
		<routestep step="31" x="350.73026" y="523.90485" z="402.00226"/>
		<routestep step="32" x="348.79272" y="517.57007" z="400.8513"/>
		<routestep step="33" x="346.67642" y="511.8168" z="399.6979"/>
		<routestep step="34" x="343.20203" y="503.03436" z="398.01382"/>
		<routestep step="35" x="341.7263" y="495.24747" z="397.7851"/>
		<routestep step="36" x="344.72507" y="493.20694" z="397.07803"/>
		<routestep step="37" x="347.3256" y="492.62433" z="396.23422"/>
		<routestep step="38" x="354.08353" y="492.07825" z="394.24344"/>
		<routestep step="39" x="359.2427" y="491.68597" z="394.3631"/>
		<routestep step="40" x="366.46872" y="490.97073" z="394.635"/>
		<routestep step="41" x="368.7956" y="491.34802" z="394.52115"/>
		<routestep step="42" x="376.17624" y="492.8878" z="393.2828"/>
		<routestep step="43" x="381.97055" y="492.8418" z="393.46396"/>
		<routestep step="44" x="382.46143" y="486.61896" z="393.49136"/>
		<routestep step="45" x="383.33694" y="480.49298" z="393.32355"/>
		<routestep step="46" x="383.5195" y="480.5009" z="393.3325"/>
		<routestep step="47" x="382.63632" y="486.7281" z="393.49768"/>
		<routestep step="48" x="382.1102" y="492.92828" z="393.46875"/>
		<routestep step="49" x="376.27313" y="492.9543" z="393.2839"/>
		<routestep step="50" x="368.7678" y="491.52832" z="394.50885"/>
		<routestep step="51" x="366.3513" y="491.11996" z="394.61377"/>
		<routestep step="52" x="359.17575" y="491.92697" z="394.33627"/>
		<routestep step="53" x="354.11313" y="492.29678" z="394.19525"/>
		<routestep step="54" x="347.33063" y="492.86807" z="396.2674"/>
		<routestep step="55" x="344.3514" y="493.65494" z="397.19083"/>
		<routestep step="56" x="341.8602" y="495.28696" z="397.7749"/>
		<routestep step="57" x="343.29794" y="502.98587" z="398.02554"/>
		<routestep step="58" x="346.72287" y="511.78366" z="399.69876"/>
		<routestep step="59" x="348.70642" y="517.7452" z="400.85953"/>
		<routestep step="60" x="350.84332" y="523.9049" z="402.0232"/>
		<routestep step="61" x="353.4491" y="533.40985" z="403.78436"/>
		<routestep step="62" x="358.06375" y="541.81555" z="407.1070"/>
		<routestep step="63" x="362.57452" y="547.13983" z="407.93262"/>
		<routestep step="64" x="367.11768" y="552.55347" z="408.1093"/>
		<routestep step="65" x="376.06494" y="558.6450" z="408.48755"/>
		<routestep step="66" x="384.3958" y="564.7017" z="408.84277"/>
		<routestep step="67" x="391.17606" y="572.17865" z="408.9311"/>
		<routestep step="68" x="395.40723" y="578.76056" z="409.0133"/>
		<routestep step="69" x="399.83652" y="588.418" z="408.67935"/>
		<routestep step="70" x="399.90503" y="596.86475" z="408.15787"/>
		<routestep step="71" x="399.32767" y="604.1342" z="408.24924"/>
		<routestep step="72" x="397.0744" y="611.7836" z="407.83917"/>
		<routestep step="73" x="393.20676" y="616.9526" z="408.54"/>
		<routestep step="74" x="389.0582" y="621.992" z="410.02374"/>
		<routestep step="75" x="386.76422" y="626.14856" z="410.7425"/>
		<routestep step="76" x="385.6357" y="633.17004" z="412.2954"/>
		<routestep step="77" x="386.3875" y="638.2403" z="412.76025"/>
		<routestep step="78" x="388.5456" y="645.4387" z="411.6623"/>
		<routestep step="79" x="393.4418" y="652.5971" z="410.52545"/>
		<routestep step="80" x="396.02054" y="662.8770" z="407.62897"/>
		<routestep step="81" x="394.32803" y="674.2254" z="405.11514"/>
		<routestep step="82" x="392.48224" y="681.0124" z="403.7238"/>
		<routestep step="83" x="391.77408" y="685.4483" z="403.0237"/>
		<routestep step="84" x="390.9944" y="691.13513" z="402.21347"/>
		<routestep step="85" x="391.06442" y="694.7809" z="402.20908"/>
		<routestep step="86" x="393.71725" y="698.4915" z="402.2158"/>
		<routestep step="87" x="398.69116" y="701.9418" z="402.2206"/>
		<routestep step="88" x="401.22348" y="705.03143" z="402.22354"/>
		<routestep step="89" x="402.9731" y="708.9972" z="402.2513"/>
		<routestep step="90" x="404.5019" y="713.4612" z="402.27365"/>
    </walker_template>
    <walker_template route_id="path_iddreadgion_02_shulackworker_7" pool="1">
	    <routestep step="1" x="589.0000" y="711.3100" z="402.22366"/>
		<routestep step="2" x="589.1699" y="708.2579" z="402.22354"/>
		<routestep step="3" x="588.1836" y="704.4317" z="402.22354"/>
		<routestep step="4" x="587.2401" y="701.9083" z="402.22354"/>
		<routestep step="5" x="585.3560" y="698.4248" z="402.21802"/>
		<routestep step="6" x="582.4274" y="694.72943" z="402.2096"/>
		<routestep step="7" x="580.5617" y="691.0647" z="402.20755"/>
		<routestep step="8" x="580.3352" y="685.35284" z="402.98587"/>
		<routestep step="9" x="579.57874" y="680.92993" z="403.67624"/>
		<routestep step="10" x="577.9341" y="674.1503" z="405.0103"/>
		<routestep step="11" x="574.38513" y="662.78986" z="407.56238"/>
		<routestep step="12" x="577.8868" y="652.5507" z="410.49973"/>
		<routestep step="13" x="581.02875" y="645.43176" z="411.61694"/>
		<routestep step="14" x="584.6676" y="638.1836" z="412.92493"/>
		<routestep step="15" x="585.26166" y="633.1164" z="412.17517"/>
		<routestep step="16" x="584.3130" y="626.08234" z="410.53012"/>
		<routestep step="17" x="582.5240" y="621.95013" z="409.88858"/>
		<routestep step="18" x="576.9817" y="616.9202" z="408.45023"/>
		<routestep step="19" x="573.86505" y="611.7397" z="407.83112"/>
		<routestep step="20" x="570.85815" y="604.0299" z="408.21997"/>
		<routestep step="21" x="570.15704" y="596.7606" z="408.10678"/>
		<routestep step="22" x="571.7738" y="588.3457" z="408.4936"/>
		<routestep step="23" x="572.06024" y="579.0720" z="409.03113"/>
		<routestep step="24" x="580.49567" y="572.11426" z="408.83652"/>
		<routestep step="25" x="587.8668" y="564.6735" z="408.74567"/>
		<routestep step="26" x="595.47534" y="558.6034" z="408.37048"/>
		<routestep step="27" x="603.89746" y="552.5784" z="408.00064"/>
		<routestep step="28" x="608.6453" y="547.3635" z="407.81122"/>
		<routestep step="29" x="610.4319" y="541.75195" z="407.3122"/>
		<routestep step="30" x="618.21796" y="533.3550" z="403.56537"/>
		<routestep step="31" x="622.1626" y="523.8269" z="401.59845"/>
		<routestep step="32" x="625.05756" y="517.4921" z="400.2998"/>
		<routestep step="33" x="627.0983" y="511.73886" z="399.12936"/>
		<routestep step="34" x="628.8083" y="502.95642" z="397.73456"/>
		<routestep step="35" x="628.6417" y="494.45288" z="397.7445"/>
		<routestep step="36" x="620.2641" y="492.2707" z="395.36728"/>
		<routestep step="37" x="609.6548" y="491.96878" z="394.30426"/>
		<routestep step="38" x="603.82733" y="492.45792" z="394.40195"/>
		<routestep step="39" x="596.37683" y="492.4716" z="393.28455"/>
		<routestep step="40" x="591.0211" y="492.78775" z="393.42206"/>
		<routestep step="41" x="588.26324" y="490.51944" z="393.5511"/>
		<routestep step="42" x="586.69214" y="487.98126" z="393.5849"/>
		<routestep step="43" x="585.4859" y="485.57013" z="393.5314"/>
		<routestep step="44" x="583.95544" y="482.37854" z="393.41476"/>
		<routestep step="45" x="584.1380" y="482.38644" z="393.4184"/>
		<routestep step="46" x="585.66077" y="485.67926" z="393.54248"/>
		<routestep step="47" x="586.8318" y="488.06775" z="393.58392"/>
		<routestep step="48" x="586.71814" y="488.06665" z="393.58615"/>
		<routestep step="49" x="588.2355" y="490.69974" z="393.55045"/>
		<routestep step="50" x="590.9037" y="492.93698" z="393.42584"/>
		<routestep step="51" x="596.3099" y="492.7126" z="393.28522"/>
		<routestep step="52" x="603.85693" y="492.67645" z="394.38425"/>
		<routestep step="53" x="609.6598" y="492.21252" z="394.27493"/>
		<routestep step="54" x="619.89044" y="492.7187" z="395.22873"/>
		<routestep step="55" x="628.77563" y="494.49237" z="397.77625"/>
		<routestep step="56" x="628.9042" y="502.90793" z="397.72455"/>
		<routestep step="57" x="627.1448" y="511.70572" z="399.12433"/>
		<routestep step="58" x="624.97125" y="517.66724" z="400.33554"/>
		<routestep step="59" x="622.27563" y="523.82697" z="401.60474"/>
		<routestep step="60" x="618.2995" y="533.3319" z="403.5646"/>
		<routestep step="61" x="610.47705" y="541.7376" z="407.2935"/>
		<routestep step="62" x="608.57574" y="547.0619" z="407.81805"/>
		<routestep step="63" x="603.94836" y="552.4755" z="407.9991"/>
		<routestep step="64" x="595.5246" y="558.5671" z="408.36847"/>
		<routestep step="65" x="587.8800" y="564.6238" z="408.74728"/>
		<routestep step="66" x="580.56586" y="572.1007" z="408.84015"/>
		<routestep step="67" x="572.1149" y="578.6826" z="408.98907"/>
		<routestep step="68" x="571.8063" y="588.3401" z="408.49112"/>
		<routestep step="69" x="570.2237" y="596.7868" z="408.10294"/>
		<routestep step="70" x="570.9237" y="604.0563" z="408.21454"/>
		<routestep step="71" x="573.78204" y="611.7057" z="407.81268"/>
		<routestep step="72" x="576.88165" y="616.87463" z="408.43536"/>
		<routestep step="73" x="582.48267" y="621.91406" z="409.88303"/>
		<routestep step="74" x="584.34845" y="626.0706" z="410.5236"/>
		<routestep step="75" x="585.2837" y="633.0921" z="412.17133"/>
		<routestep step="76" x="584.68604" y="638.16235" z="412.93466"/>
		<routestep step="77" x="581.0273" y="645.3608" z="411.6236"/>
		<routestep step="78" x="577.87555" y="652.51917" z="410.5072"/>
		<routestep step="79" x="574.4315" y="662.7991" z="407.55957"/>
		<routestep step="80" x="578.0029" y="674.14746" z="405.00983"/>
		<routestep step="81" x="579.64667" y="680.93445" z="403.6753"/>
		<routestep step="82" x="580.39935" y="685.37036" z="402.98322"/>
		<routestep step="83" x="580.61456" y="691.0572" z="402.20755"/>
		<routestep step="84" x="582.46356" y="694.70294" z="402.20956"/>
		<routestep step="85" x="585.3567" y="698.4136" z="402.2180"/>
		<routestep step="86" x="587.2666" y="701.86383" z="402.22354"/>
		<routestep step="87" x="588.15186" y="704.3840" z="402.2281"/>
		<routestep step="88" x="589.1951" y="708.2396" z="402.22354"/>
		<routestep step="89" x="589.1019" y="711.3412" z="402.22388"/>
    </walker_template>
    <walker_template route_id="path_iddreadgion_02_shulackworker_8" pool="1">
	    <routestep step="1" x="588.2000" y="713.4400" z="402.22894"/>
		<routestep step="2" x="588.6592" y="708.6851" z="402.22354"/>
		<routestep step="3" x="587.9456" y="704.43286" z="402.22354"/>
		<routestep step="4" x="587.00214" y="701.9095" z="402.22354"/>
		<routestep step="5" x="585.11804" y="698.42596" z="402.21793"/>
		<routestep step="6" x="582.18945" y="694.7306" z="402.20956"/>
		<routestep step="7" x="580.3237" y="691.06586" z="402.20755"/>
		<routestep step="8" x="580.0972" y="685.3540" z="402.98483"/>
		<routestep step="9" x="579.34076" y="680.9311" z="403.67706"/>
		<routestep step="10" x="577.6961" y="674.1515" z="405.0140"/>
		<routestep step="11" x="574.14716" y="662.791" z="407.56528"/>
		<routestep step="12" x="577.6488" y="652.5519" z="410.49197"/>
		<routestep step="13" x="580.7908" y="645.4329" z="411.6110"/>
		<routestep step="14" x="584.4296" y="638.18475" z="412.85046"/>
		<routestep step="15" x="585.0237" y="633.11755" z="412.14325"/>
		<routestep step="16" x="584.0750" y="626.0835" z="410.55835"/>
		<routestep step="17" x="582.2860" y="621.9513" z="409.89664"/>
		<routestep step="18" x="576.7438" y="616.9214" z="408.44525"/>
		<routestep step="19" x="573.6271" y="611.74084" z="407.77826"/>
		<routestep step="20" x="570.6202" y="604.03107" z="408.22366"/>
		<routestep step="21" x="569.91907" y="596.7618" z="408.11624"/>
		<routestep step="22" x="571.5358" y="588.34686" z="408.51456"/>
		<routestep step="23" x="571.82227" y="579.0732" z="409.0135"/>
		<routestep step="24" x="580.2577" y="572.1154" z="408.82727"/>
		<routestep step="25" x="587.62885" y="564.6747" z="408.7480"/>
		<routestep step="26" x="595.23737" y="558.60455" z="408.37964"/>
		<routestep step="27" x="603.6595" y="552.5796" z="408.01294"/>
		<routestep step="28" x="608.40735" y="547.3647" z="407.82452"/>
		<routestep step="29" x="610.1939" y="541.7531" z="407.3414"/>
		<routestep step="30" x="617.9800" y="533.35614" z="403.55627"/>
		<routestep step="31" x="621.9246" y="523.82806" z="401.58554"/>
		<routestep step="32" x="624.8196" y="517.4933" z="400.28894"/>
		<routestep step="33" x="626.86035" y="511.74002" z="399.11795"/>
		<routestep step="34" x="628.5703" y="502.95758" z="397.76154"/>
		<routestep step="35" x="628.40375" y="494.45404" z="397.69376"/>
		<routestep step="36" x="620.0261" y="492.27185" z="395.28976"/>
		<routestep step="37" x="609.4168" y="491.96994" z="394.30893"/>
		<routestep step="38" x="603.58936" y="492.45908" z="394.40915"/>
		<routestep step="39" x="596.13885" y="492.47275" z="393.28998"/>
		<routestep step="40" x="590.78314" y="492.7889" z="393.42972"/>
		<routestep step="41" x="588.02527" y="490.5206" z="393.5607"/>
		<routestep step="42" x="586.45416" y="487.98242" z="393.5906"/>
		<routestep step="43" x="585.2479" y="485.5713" z="393.5194"/>
		<routestep step="44" x="583.71747" y="482.3797" z="393.41052"/>
		<routestep step="45" x="583.9000" y="482.3876" z="393.41412"/>
		<routestep step="46" x="585.4228" y="485.68042" z="393.53046"/>
		<routestep step="47" x="586.5938" y="488.0689" z="393.58865"/>
		<routestep step="48" x="586.48016" y="488.0678" z="393.59167"/>
		<routestep step="49" x="587.9975" y="490.7009" z="393.56006"/>
		<routestep step="50" x="590.6657" y="492.93814" z="393.43347"/>
		<routestep step="51" x="596.0719" y="492.71375" z="393.29065"/>
		<routestep step="52" x="603.61896" y="492.6776" z="394.39273"/>
		<routestep step="53" x="609.4218" y="492.21368" z="394.2796"/>
		<routestep step="54" x="619.65247" y="492.71985" z="395.14905"/>
		<routestep step="55" x="628.53766" y="494.49353" z="397.72195"/>
		<routestep step="56" x="628.6662" y="502.9091" z="397.7515"/>
		<routestep step="57" x="626.9068" y="511.70688" z="399.1129"/>
		<routestep step="58" x="624.7333" y="517.6684" z="400.32468"/>
		<routestep step="59" x="622.03766" y="523.8281" z="401.5918"/>
		<routestep step="60" x="618.0615" y="533.33307" z="403.55167"/>
		<routestep step="61" x="610.2391" y="541.7388" z="407.3337"/>
		<routestep step="62" x="608.33777" y="547.06305" z="407.83035"/>
		<routestep step="63" x="603.7104" y="552.4767" z="408.0114"/>
		<routestep step="64" x="595.2866" y="558.56824" z="408.37784"/>
		<routestep step="65" x="587.6420" y="564.62494" z="408.74796"/>
		<routestep step="66" x="580.3279" y="572.10187" z="408.82523"/>
		<routestep step="67" x="571.87695" y="578.6838" z="408.97144"/>
		<routestep step="68" x="571.5683" y="588.34125" z="408.51212"/>
		<routestep step="69" x="569.9857" y="596.78796" z="408.11517"/>
		<routestep step="70" x="570.6857" y="604.05743" z="408.21823"/>
		<routestep step="71" x="573.54407" y="611.70685" z="407.7640"/>
		<routestep step="72" x="576.6437" y="616.8758" z="408.4304"/>
		<routestep step="73" x="582.2447" y="621.9152" z="409.89105"/>
		<routestep step="74" x="584.1105" y="626.0718" z="410.55182"/>
		<routestep step="75" x="585.0457" y="633.09326" z="412.1394"/>
		<routestep step="76" x="584.44806" y="638.1635" z="412.85834"/>
		<routestep step="77" x="580.7893" y="645.36194" z="411.61765"/>
		<routestep step="78" x="577.6376" y="652.5203" z="410.49945"/>
		<routestep step="79" x="574.19354" y="662.80023" z="407.56247"/>
		<routestep step="80" x="577.76495" y="674.1486" z="405.01352"/>
		<routestep step="81" x="579.4087" y="680.9356" z="403.67612"/>
		<routestep step="82" x="580.1614" y="685.3715" z="402.9822"/>
		<routestep step="83" x="580.3766" y="691.05835" z="402.20755"/>
		<routestep step="84" x="582.2256" y="694.7041" z="402.20953"/>
		<routestep step="85" x="585.1187" y="698.41473" z="402.22162"/>
		<routestep step="86" x="587.0286" y="701.8650" z="402.22354"/>
		<routestep step="87" x="587.9139" y="704.38513" z="402.22354"/>
		<routestep step="88" x="588.6844" y="708.6669" z="402.22354"/>
		<routestep step="89" x="588.30194" y="713.4712" z="402.2292"/>
    </walker_template>
</npc_walker>